Workbook

Sheet Sheet1
A1: Brand Partner Order Projections
A3: Item Total by Month
A4: JUVIA'S PLACE (52853)
A5: Report Generated: 1/28/2026 8:15:30 PM
A7: General Information | M7: 2026 P01 | N7: 2026 P02 | O7: 2026 P03 | P7: 2026 P04 | Q7: 2026 P05 | R7: 2026 P06 | S7: 2026 P07 | T7: 2026 P08 | U7: 2026 P09 | V7: 2026 P10 | W7: 2026 P11 | X7: 2026 P12
A8: UPC# | B8: ULTA Item# | C8: ULTA Item Description | E8: Brand Partner SKU# | F8: Department | G8: Brand # | H8: Retail Item Rank | I8: Feature Code | J8: Season Code | K8: Purchase Cost (Average) | L8: Retail Price (Current) | M8: February | N8: March | O8: April | P8: May | Q8: June | R8: July | S8: August | T8: September | U8: October | V8: November | W8: December | X8: January | AJ8: Current | AK8: Past | AL8: Delta
A9: Overall Result | M9: 178126 | N9: 214138 | O9: 237182 | P9: 205374 | Q9: 215320 | R9: 269098 | S9: 221360 | T9: 231522 | U9: 317806 | V9: 367876 | W9: 249064 | X9: 357776 | AA9: 13 | AB9: =AA9+1 -> 14 | AC9: =AB9+1 -> 15 | AD9: =AC9+1 -> 16 | AE9: =AD9+1 -> 17 | AF9: =AE9+1 -> 18 | AG9: =AF9+1 -> 19 | AH9: =AG9+1 -> 20
A10: 869001000347 | B10: 2536080 | C10: THE SAHARAN BLUSH PALETTE | E10: 1000361 | F10: 021 | G10: 3453 - JUVIA'S PLACE | I10: X | J10: BASC | K10: 9 | L10: 18 | M10: 0 | N10: 0 | O10: 0 | P10: 0 | Q10: 0 | R10: 0 | S10: 0 | T10: 0 | U10: 0 | V10: 0 | W10: 0 | X10: 0 | Z10: =VLOOKUP(E10,Sheet2!$A$1:$A$39,1,0) -> #N/A | AA10: =VLOOKUP($E10,[1]Sheet1!$E$10:$X$629,AA$9,0) -> 0 | AB10: =VLOOKUP($E10,[1]Sheet1!$E$10:$X$629,AB$9,0) -> 0 | AC10: =VLOOKUP($E10,[1]Sheet1!$E$10:$X$629,AC$9,0) -> 0 | AD10: =VLOOKUP($E10,[1]Sheet1!$E$10:$X$629,AD$9,0) -> 0 | AE10: =VLOOKUP($E10,[1]Sheet1!$E$10:$X$629,AE$9,0) -> 0 | AF10: =VLOOKUP($E10,[1]Sheet1!$E$10:$X$629,AF$9,0) -> 0 | AG10: =VLOOKUP($E10,[1]Sheet1!$E$10:$X$629,AG$9,0) -> 0 | AH10: =VLOOKUP($E10,[1]Sheet1!$E$10:$X$629,AH$9,0) -> 0 | AJ10: =SUM(M10:T10) -> 0 | AK10: =SUM(AA10:AH10) -> 0 | AL10: =IFERROR(AJ10-AK10,0) -> 0
A11: 869001000248 | B11: 2536081 | C11: THE MASQUERADE MINI EYESHADOW PALETTE | E11: 1000091 | F11: 021 | G11: 3453 - JUVIA'S PLACE | H11: C | I11: DI | J11: BASC | K11: 12.5 | L11: 2.5 | M11: 0 | N11: 0 | O11: 0 | P11: 0 | Q11: 0 | R11: 0 | S11: 0 | T11: 0 | U11: 0 | V11: 0 | W11: 0 | X11: 0 | Z11: =VLOOKUP(E11,Sheet2!$A$1:$A$39,1,0) -> #N/A | AA11: =VLOOKUP($E11,[1]Sheet1!$E$10:$X$629,AA$9,0) -> 0 | AB11: =VLOOKUP($E11,[1]Sheet1!$E$10:$X$629,AB$9,0) -> 0 | AC11: =VLOOKUP($E11,[1]Sheet1!$E$10:$X$629,AC$9,0) -> 0 | AD11: =VLOOKUP($E11,[1]Sheet1!$E$10:$X$629,AD$9,0) -> 0 | AE11: =VLOOKUP($E11,[1]Sheet1!$E$10:$X$629,AE$9,0) -> 0 | AF11: =VLOOKUP($E11,[1]Sheet1!$E$10:$X$629,AF$9,0) -> 0 | AG11: =VLOOKUP($E11,[1]Sheet1!$E$10:$X$629,AG$9,0) -> 0 | AH11: =VLOOKUP($E11,[1]Sheet1!$E$10:$X$629,AH$9,0) -> 0 | AJ11: =SUM(M11:T11) -> 0 | AK11: =SUM(AA11:AH11) -> 0 | AL11: =IFERROR(AJ11-AK11,0) -> 0
A12: 869001000316 | B12: 2536082 | C12: THE ZULU EYESHADOW PALETTE 1.14OZ | E12: 1000369 | F12: 021 | G12: 3453 - JUVIA'S PLACE | H12: E | I12: A | J12: BASC | K12: 12.5 | L12: 25 | M12: 720 | N12: 1008 | O12: 1152 | P12: 936 | Q12: 720 | R12: 792 | S12: 720 | T12: 1008 | U12: 1224 | V12: 1944 | W12: 648 | X12: 1872 | Z12: =VLOOKUP(E12,Sheet2!$A$1:$A$39,1,0) -> #N/A | AA12: =VLOOKUP($E12,[1]Sheet1!$E$10:$X$629,AA$9,0) -> 720 | AB12: =VLOOKUP($E12,[1]Sheet1!$E$10:$X$629,AB$9,0) -> 792 | AC12: =VLOOKUP($E12,[1]Sheet1!$E$10:$X$629,AC$9,0) -> 1008 | AD12: =VLOOKUP($E12,[1]Sheet1!$E$10:$X$629,AD$9,0) -> 720 | AE12: =VLOOKUP($E12,[1]Sheet1!$E$10:$X$629,AE$9,0) -> 576 | AF12: =VLOOKUP($E12,[1]Sheet1!$E$10:$X$629,AF$9,0) -> 648 | AG12: =VLOOKUP($E12,[1]Sheet1!$E$10:$X$629,AG$9,0) -> 648 | AH12: =VLOOKUP($E12,[1]Sheet1!$E$10:$X$629,AH$9,0) -> 216 | AJ12: =SUM(M12:T12) -> 7056 | AK12: =SUM(AA12:AH12) -> 5328 | AL12: =IFERROR(AJ12-AK12,0) -> 1728
A13: 869001000231 | B13: 2536083 | C13: THE SAHARAN EYESHADOW PALETTE SAHARAN | E13: 1000359 | F13: 021 | G13: 3453 - JUVIA'S PLACE | H13: F | I13: A | J13: BASC | K13: 12.5 | L13: 25 | M13: 288 | N13: 480 | O13: 480 | P13: 384 | Q13: 288 | R13: 384 | S13: 384 | T13: 384 | U13: 480 | V13: 1344 | W13: 672 | X13: 1056 | Z13: =VLOOKUP(E13,Sheet2!$A$1:$A$39,1,0) -> #N/A | AA13: =VLOOKUP($E13,[1]Sheet1!$E$10:$X$629,AA$9,0) -> 384 | AB13: =VLOOKUP($E13,[1]Sheet1!$E$10:$X$629,AB$9,0) -> 192 | AC13: =VLOOKUP($E13,[1]Sheet1!$E$10:$X$629,AC$9,0) -> 576 | AD13: =VLOOKUP($E13,[1]Sheet1!$E$10:$X$629,AD$9,0) -> 288 | AE13: =VLOOKUP($E13,[1]Sheet1!$E$10:$X$629,AE$9,0) -> 288 | AF13: =VLOOKUP($E13,[1]Sheet1!$E$10:$X$629,AF$9,0) -> 480 | AG13: =VLOOKUP($E13,[1]Sheet1!$E$10:$X$629,AG$9,0) -> 192 | AH13: =VLOOKUP($E13,[1]Sheet1!$E$10:$X$629,AH$9,0) -> 192 | AJ13: =SUM(M13:T13) -> 3072 | AK13: =SUM(AA13:AH13) -> 2592 | AL13: =IFERROR(AJ13-AK13,0) -> 480
A14: 857494007271 | B14: 2536084 | C14: THE MAGIC MINI EYESHADOW PALETTE | E14: 4007271 | F14: 021 | G14: 3453 - JUVIA'S PLACE | I14: X | J14: BASC | K14: 12.5 | L14: 12.49 | M14: 0 | N14: 0 | O14: 0 | P14: 0 | Q14: 0 | R14: 0 | S14: 0 | T14: 0 | U14: 0 | V14: 0 | W14: 0 | X14: 0 | Z14: =VLOOKUP(E14,Sheet2!$A$1:$A$39,1,0) -> #N/A | AA14: =VLOOKUP($E14,[1]Sheet1!$E$10:$X$629,AA$9,0) -> 0 | AB14: =VLOOKUP($E14,[1]Sheet1!$E$10:$X$629,AB$9,0) -> 0 | AC14: =VLOOKUP($E14,[1]Sheet1!$E$10:$X$629,AC$9,0) -> 0 | AD14: =VLOOKUP($E14,[1]Sheet1!$E$10:$X$629,AD$9,0) -> 0 | AE14: =VLOOKUP($E14,[1]Sheet1!$E$10:$X$629,AE$9,0) -> 0 | AF14: =VLOOKUP($E14,[1]Sheet1!$E$10:$X$629,AF$9,0) -> 0 | AG14: =VLOOKUP($E14,[1]Sheet1!$E$10:$X$629,AG$9,0) -> 0 | AH14: =VLOOKUP($E14,[1]Sheet1!$E$10:$X$629,AH$9,0) -> 0 | AJ14: =SUM(M14:T14) -> 0 | AK14: =SUM(AA14:AH14) -> 0 | AL14: =IFERROR(AJ14-AK14,0) -> 0
A15: 869001000279 | B15: 2536085 | C15: THE SAHARAN BLUSH PALETTE | E15: 1000360 | F15: 021 | G15: 3453 - JUVIA'S PLACE | I15: DI | J15: BASC | K15: 9 | L15: 18 | M15: 0 | N15: 0 | O15: 0 | P15: 0 | Q15: 0 | R15: 0 | S15: 0 | T15: 0 | U15: 0 | V15: 0 | W15: 0 | X15: 0 | Z15: =VLOOKUP(E15,Sheet2!$A$1:$A$39,1,0) -> #N/A | AA15: =VLOOKUP($E15,[1]Sheet1!$E$10:$X$629,AA$9,0) -> 0 | AB15: =VLOOKUP($E15,[1]Sheet1!$E$10:$X$629,AB$9,0) -> 0 | AC15: =VLOOKUP($E15,[1]Sheet1!$E$10:$X$629,AC$9,0) -> 0 | AD15: =VLOOKUP($E15,[1]Sheet1!$E$10:$X$629,AD$9,0) -> 0 | AE15: =VLOOKUP($E15,[1]Sheet1!$E$10:$X$629,AE$9,0) -> 0 | AF15: =VLOOKUP($E15,[1]Sheet1!$E$10:$X$629,AF$9,0) -> 0 | AG15: =VLOOKUP($E15,[1]Sheet1!$E$10:$X$629,AG$9,0) -> 0 | AH15: =VLOOKUP($E15,[1]Sheet1!$E$10:$X$629,AH$9,0) -> 0 | AJ15: =SUM(M15:T15) -> 0 | AK15: =SUM(AA15:AH15) -> 0 | AL15: =IFERROR(AJ15-AK15,0) -> 0
A16: 857494007097 | B16: 2536086 | C16: THE EYESHADOW PALETTE | E16: 1000338 | F16: 021 | G16: 3453 - JUVIA'S PLACE | I16: X | J16: BASC | K16: 10 | L16: 20 | M16: 0 | N16: 0 | O16: 0 | P16: 0 | Q16: 0 | R16: 0 | S16: 0 | T16: 0 | U16: 0 | V16: 0 | W16: 0 | X16: 0 | Z16: =VLOOKUP(E16,Sheet2!$A$1:$A$39,1,0) -> #N/A | AA16: =VLOOKUP($E16,[1]Sheet1!$E$10:$X$629,AA$9,0) -> 0 | AB16: =VLOOKUP($E16,[1]Sheet1!$E$10:$X$629,AB$9,0) -> 0 | AC16: =VLOOKUP($E16,[1]Sheet1!$E$10:$X$629,AC$9,0) -> 0 | AD16: =VLOOKUP($E16,[1]Sheet1!$E$10:$X$629,AD$9,0) -> 0 | AE16: =VLOOKUP($E16,[1]Sheet1!$E$10:$X$629,AE$9,0) -> 0 | AF16: =VLOOKUP($E16,[1]Sheet1!$E$10:$X$629,AF$9,0) -> 0 | AG16: =VLOOKUP($E16,[1]Sheet1!$E$10:$X$629,AG$9,0) -> 0 | AH16: =VLOOKUP($E16,[1]Sheet1!$E$10:$X$629,AH$9,0) -> 0 | AJ16: =SUM(M16:T16) -> 0 | AK16: =SUM(AA16:AH16) -> 0 | AL16: =IFERROR(AJ16-AK16,0) -> 0
A17: 857494007288 | B17: 2536087 | C17: THE WARRIOR EYESHADOW PALETTE WARRIOR | E17: 1000367 | F17: 021 | G17: 3453 - JUVIA'S PLACE | H17: E | I17: A | J17: BASC | K17: 12.5 | L17: 25 | M17: 936 | N17: 1296 | O17: 1152 | P17: 1080 | Q17: 1152 | R17: 1368 | S17: 1368 | T17: 1296 | U17: 2376 | V17: 2448 | W17: 792 | X17: 2520 | Z17: =VLOOKUP(E17,Sheet2!$A$1:$A$39,1,0) -> #N/A | AA17: =VLOOKUP($E17,[1]Sheet1!$E$10:$X$629,AA$9,0) -> 1296 | AB17: =VLOOKUP($E17,[1]Sheet1!$E$10:$X$629,AB$9,0) -> 1584 | AC17: =VLOOKUP($E17,[1]Sheet1!$E$10:$X$629,AC$9,0) -> 1800 | AD17: =VLOOKUP($E17,[1]Sheet1!$E$10:$X$629,AD$9,0) -> 1584 | AE17: =VLOOKUP($E17,[1]Sheet1!$E$10:$X$629,AE$9,0) -> 1368 | AF17: =VLOOKUP($E17,[1]Sheet1!$E$10:$X$629,AF$9,0) -> 1872 | AG17: =VLOOKUP($E17,[1]Sheet1!$E$10:$X$629,AG$9,0) -> 1872 | AH17: =VLOOKUP($E17,[1]Sheet1!$E$10:$X$629,AH$9,0) -> 720 | AJ17: =SUM(M17:T17) -> 9648 | AK17: =SUM(AA17:AH17) -> 12096 | AL17: =IFERROR(AJ17-AK17,0) -> -2448
A18: 857494007295 | B18: 2536088 | C18: THE WARRIOR EYESHADOW PALETTE WARRIOR II | E18: 1000368 | F18: 021 | G18: 3453 - JUVIA'S PLACE | H18: E | I18: A | J18: BASC | K18: 12.5 | L18: 25 | M18: 720 | N18: 1008 | O18: 936 | P18: 936 | Q18: 936 | R18: 1152 | S18: 936 | T18: 1080 | U18: 1368 | V18: 2160 | W18: 720 | X18: 2016 | Z18: =VLOOKUP(E18,Sheet2!$A$1:$A$39,1,0) -> #N/A | AA18: =VLOOKUP($E18,[1]Sheet1!$E$10:$X$629,AA$9,0) -> 936 | AB18: =VLOOKUP($E18,[1]Sheet1!$E$10:$X$629,AB$9,0) -> 1008 | AC18: =VLOOKUP($E18,[1]Sheet1!$E$10:$X$629,AC$9,0) -> 1152 | AD18: =VLOOKUP($E18,[1]Sheet1!$E$10:$X$629,AD$9,0) -> 864 | AE18: =VLOOKUP($E18,[1]Sheet1!$E$10:$X$629,AE$9,0) -> 936 | AF18: =VLOOKUP($E18,[1]Sheet1!$E$10:$X$629,AF$9,0) -> 1224 | AG18: =VLOOKUP($E18,[1]Sheet1!$E$10:$X$629,AG$9,0) -> 1080 | AH18: =VLOOKUP($E18,[1]Sheet1!$E$10:$X$629,AH$9,0) -> 504 | AJ18: =SUM(M18:T18) -> 7704 | AK18: =SUM(AA18:AH18) -> 7704 | AL18: =IFERROR(AJ18-AK18,0) -> 0
A19: 857494007523 | B19: 2536090 | C19: AFRIQUE EYESHADOW PALETTE | E19: 1000085 | F19: 021 | G19: 3453 - JUVIA'S PLACE | I19: X | J19: BASC | K19: 10 | L19: 20 | M19: 0 | N19: 0 | O19: 0 | P19: 0 | Q19: 0 | R19: 0 | S19: 0 | T19: 0 | U19: 0 | V19: 0 | W19: 0 | X19: 0 | Z19: =VLOOKUP(E19,Sheet2!$A$1:$A$39,1,0) -> #N/A | AA19: =VLOOKUP($E19,[1]Sheet1!$E$10:$X$629,AA$9,0) -> 0 | AB19: =VLOOKUP($E19,[1]Sheet1!$E$10:$X$629,AB$9,0) -> 0 | AC19: =VLOOKUP($E19,[1]Sheet1!$E$10:$X$629,AC$9,0) -> 0 | AD19: =VLOOKUP($E19,[1]Sheet1!$E$10:$X$629,AD$9,0) -> 0 | AE19: =VLOOKUP($E19,[1]Sheet1!$E$10:$X$629,AE$9,0) -> 0 | AF19: =VLOOKUP($E19,[1]Sheet1!$E$10:$X$629,AF$9,0) -> 0 | AG19: =VLOOKUP($E19,[1]Sheet1!$E$10:$X$629,AG$9,0) -> 0 | AH19: =VLOOKUP($E19,[1]Sheet1!$E$10:$X$629,AH$9,0) -> 0 | AJ19: =SUM(M19:T19) -> 0 | AK19: =SUM(AA19:AH19) -> 0 | AL19: =IFERROR(AJ19-AK19,0) -> 0
A20: 857494007516 | B20: 2536093 | C20: BELLA BLUSH | E20: 1000611 | F20: 021 | G20: 3453 - JUVIA'S PLACE | I20: DI | J20: BASC | K20: 4 | L20: 8 | M20: 0 | N20: 0 | O20: 0 | P20: 0 | Q20: 0 | R20: 0 | S20: 0 | T20: 0 | U20: 0 | V20: 0 | W20: 0 | X20: 0 | Z20: =VLOOKUP(E20,Sheet2!$A$1:$A$39,1,0) -> #N/A | AA20: =VLOOKUP($E20,[1]Sheet1!$E$10:$X$629,AA$9,0) -> 0 | AB20: =VLOOKUP($E20,[1]Sheet1!$E$10:$X$629,AB$9,0) -> 0 | AC20: =VLOOKUP($E20,[1]Sheet1!$E$10:$X$629,AC$9,0) -> 0 | AD20: =VLOOKUP($E20,[1]Sheet1!$E$10:$X$629,AD$9,0) -> 0 | AE20: =VLOOKUP($E20,[1]Sheet1!$E$10:$X$629,AE$9,0) -> 0 | AF20: =VLOOKUP($E20,[1]Sheet1!$E$10:$X$629,AF$9,0) -> 0 | AG20: =VLOOKUP($E20,[1]Sheet1!$E$10:$X$629,AG$9,0) -> 0 | AH20: =VLOOKUP($E20,[1]Sheet1!$E$10:$X$629,AH$9,0) -> 0 | AJ20: =SUM(M20:T20) -> 0 | AK20: =SUM(AA20:AH20) -> 0 | AL20: =IFERROR(AJ20-AK20,0) -> 0
A21: 857494007417 | B21: 2536094 | C21: THE TRIBE HIGHLIGHTER | E21: 1000371 | F21: 021 | G21: 3453 - JUVIA'S PLACE | I21: X | J21: BASC | K21: 7.5 | L21: 15 | M21: 0 | N21: 0 | O21: 0 | P21: 0 | Q21: 0 | R21: 0 | S21: 0 | T21: 0 | U21: 0 | V21: 0 | W21: 0 | X21: 0 | Z21: =VLOOKUP(E21,Sheet2!$A$1:$A$39,1,0) -> #N/A | AA21: =VLOOKUP($E21,[1]Sheet1!$E$10:$X$629,AA$9,0) -> 0 | AB21: =VLOOKUP($E21,[1]Sheet1!$E$10:$X$629,AB$9,0) -> 0 | AC21: =VLOOKUP($E21,[1]Sheet1!$E$10:$X$629,AC$9,0) -> 0 | AD21: =VLOOKUP($E21,[1]Sheet1!$E$10:$X$629,AD$9,0) -> 0 | AE21: =VLOOKUP($E21,[1]Sheet1!$E$10:$X$629,AE$9,0) -> 0 | AF21: =VLOOKUP($E21,[1]Sheet1!$E$10:$X$629,AF$9,0) -> 0 | AG21: =VLOOKUP($E21,[1]Sheet1!$E$10:$X$629,AG$9,0) -> 0 | AH21: =VLOOKUP($E21,[1]Sheet1!$E$10:$X$629,AH$9,0) -> 0 | AJ21: =SUM(M21:T21) -> 0 | AK21: =SUM(AA21:AH21) -> 0 | AL21: =IFERROR(AJ21-AK21,0) -> 0
A22: 857494007400 | B22: 2536095 | C22: THE TRIBE HIGHLIGHTER | E22: 1000370 | F22: 021 | G22: 3453 - JUVIA'S PLACE | I22: DI | J22: BASC | K22: 7.5 | L22: 15 | M22: 0 | N22: 0 | O22: 0 | P22: 0 | Q22: 0 | R22: 0 | S22: 0 | T22: 0 | U22: 0 | V22: 0 | W22: 0 | X22: 0 | Z22: =VLOOKUP(E22,Sheet2!$A$1:$A$39,1,0) -> #N/A | AA22: =VLOOKUP($E22,[1]Sheet1!$E$10:$X$629,AA$9,0) -> 0 | AB22: =VLOOKUP($E22,[1]Sheet1!$E$10:$X$629,AB$9,0) -> 0 | AC22: =VLOOKUP($E22,[1]Sheet1!$E$10:$X$629,AC$9,0) -> 0 | AD22: =VLOOKUP($E22,[1]Sheet1!$E$10:$X$629,AD$9,0) -> 0 | AE22: =VLOOKUP($E22,[1]Sheet1!$E$10:$X$629,AE$9,0) -> 0 | AF22: =VLOOKUP($E22,[1]Sheet1!$E$10:$X$629,AF$9,0) -> 0 | AG22: =VLOOKUP($E22,[1]Sheet1!$E$10:$X$629,AG$9,0) -> 0 | AH22: =VLOOKUP($E22,[1]Sheet1!$E$10:$X$629,AH$9,0) -> 0 | AJ22: =SUM(M22:T22) -> 0 | AK22: =SUM(AA22:AH22) -> 0 | AL22: =IFERROR(AJ22-AK22,0) -> 0
A23: 857494007493 | B23: 2536096 | C23: THE HEROINE GLOW HIGHLIGHTER GLOW 2 | E23: 1000189 | F23: 021 | G23: 3453 - JUVIA'S PLACE | I23: X | J23: BASC | K23: 8.5 | L23: 17 | M23: 0 | N23: 0 | O23: 0 | P23: 0 | Q23: 0 | R23: 0 | S23: 0 | T23: 0 | U23: 0 | V23: 0 | W23: 0 | X23: 0 | Z23: =VLOOKUP(E23,Sheet2!$A$1:$A$39,1,0) -> #N/A | AA23: =VLOOKUP($E23,[1]Sheet1!$E$10:$X$629,AA$9,0) -> 0 | AB23: =VLOOKUP($E23,[1]Sheet1!$E$10:$X$629,AB$9,0) -> 0 | AC23: =VLOOKUP($E23,[1]Sheet1!$E$10:$X$629,AC$9,0) -> 0 | AD23: =VLOOKUP($E23,[1]Sheet1!$E$10:$X$629,AD$9,0) -> 0 | AE23: =VLOOKUP($E23,[1]Sheet1!$E$10:$X$629,AE$9,0) -> 0 | AF23: =VLOOKUP($E23,[1]Sheet1!$E$10:$X$629,AF$9,0) -> 0 | AG23: =VLOOKUP($E23,[1]Sheet1!$E$10:$X$629,AG$9,0) -> 0 | AH23: =VLOOKUP($E23,[1]Sheet1!$E$10:$X$629,AH$9,0) -> 0 | AJ23: =SUM(M23:T23) -> 0 | AK23: =SUM(AA23:AH23) -> 0 | AL23: =IFERROR(AJ23-AK23,0) -> 0
A24: 857494007462 | B24: 2536097 | C24: THE WARRIOR EYESHADOW PALETTE WARRIOR III | E24: 1000109 | F24: 021 | G24: 3453 - JUVIA'S PLACE | I24: X | J24: BASC | K24: 10 | L24: 6.25 | M24: 0 | N24: 0 | O24: 0 | P24: 0 | Q24: 0 | R24: 0 | S24: 0 | T24: 0 | U24: 0 | V24: 0 | W24: 0 | X24: 0 | Z24: =VLOOKUP(E24,Sheet2!$A$1:$A$39,1,0) -> #N/A | AA24: =VLOOKUP($E24,[1]Sheet1!$E$10:$X$629,AA$9,0) -> 0 | AB24: =VLOOKUP($E24,[1]Sheet1!$E$10:$X$629,AB$9,0) -> 0 | AC24: =VLOOKUP($E24,[1]Sheet1!$E$10:$X$629,AC$9,0) -> 0 | AD24: =VLOOKUP($E24,[1]Sheet1!$E$10:$X$629,AD$9,0) -> 0 | AE24: =VLOOKUP($E24,[1]Sheet1!$E$10:$X$629,AE$9,0) -> 0 | AF24: =VLOOKUP($E24,[1]Sheet1!$E$10:$X$629,AF$9,0) -> 0 | AG24: =VLOOKUP($E24,[1]Sheet1!$E$10:$X$629,AG$9,0) -> 0 | AH24: =VLOOKUP($E24,[1]Sheet1!$E$10:$X$629,AH$9,0) -> 0 | AJ24: =SUM(M24:T24) -> 0 | AK24: =SUM(AA24:AH24) -> 0 | AL24: =IFERROR(AJ24-AK24,0) -> 0
A25: 857494007486 | B25: 2536098 | C25: THE HEROINE GLOW HIGHLIGHTER GLOW 1 | E25: 1000187 | F25: 021 | G25: 3453 - JUVIA'S PLACE | I25: X | J25: BASC | K25: 8.5 | L25: 17 | M25: 0 | N25: 0 | O25: 0 | P25: 0 | Q25: 0 | R25: 0 | S25: 0 | T25: 0 | U25: 0 | V25: 0 | W25: 0 | X25: 0 | Z25: =VLOOKUP(E25,Sheet2!$A$1:$A$39,1,0) -> #N/A | AA25: =VLOOKUP($E25,[1]Sheet1!$E$10:$X$629,AA$9,0) -> 0 | AB25: =VLOOKUP($E25,[1]Sheet1!$E$10:$X$629,AB$9,0) -> 0 | AC25: =VLOOKUP($E25,[1]Sheet1!$E$10:$X$629,AC$9,0) -> 0 | AD25: =VLOOKUP($E25,[1]Sheet1!$E$10:$X$629,AD$9,0) -> 0 | AE25: =VLOOKUP($E25,[1]Sheet1!$E$10:$X$629,AE$9,0) -> 0 | AF25: =VLOOKUP($E25,[1]Sheet1!$E$10:$X$629,AF$9,0) -> 0 | AG25: =VLOOKUP($E25,[1]Sheet1!$E$10:$X$629,AG$9,0) -> 0 | AH25: =VLOOKUP($E25,[1]Sheet1!$E$10:$X$629,AH$9,0) -> 0 | AJ25: =SUM(M25:T25) -> 0 | AK25: =SUM(AA25:AH25) -> 0 | AL25: =IFERROR(AJ25-AK25,0) -> 0
A26: 857494007233 | B26: 2536100 | C26: THE ROYALTY GLOW LOOSE HIGHLIGHTER | E26: 1000810 | F26: 021 | G26: 3453 - JUVIA'S PLACE | I26: X | J26: BASC | K26: 7 | L26: 14 | M26: 0 | N26: 0 | O26: 0 | P26: 0 | Q26: 0 | R26: 0 | S26: 0 | T26: 0 | U26: 0 | V26: 0 | W26: 0 | X26: 0 | Z26: =VLOOKUP(E26,Sheet2!$A$1:$A$39,1,0) -> #N/A | AA26: =VLOOKUP($E26,[1]Sheet1!$E$10:$X$629,AA$9,0) -> 0 | AB26: =VLOOKUP($E26,[1]Sheet1!$E$10:$X$629,AB$9,0) -> 0 | AC26: =VLOOKUP($E26,[1]Sheet1!$E$10:$X$629,AC$9,0) -> 0 | AD26: =VLOOKUP($E26,[1]Sheet1!$E$10:$X$629,AD$9,0) -> 0 | AE26: =VLOOKUP($E26,[1]Sheet1!$E$10:$X$629,AE$9,0) -> 0 | AF26: =VLOOKUP($E26,[1]Sheet1!$E$10:$X$629,AF$9,0) -> 0 | AG26: =VLOOKUP($E26,[1]Sheet1!$E$10:$X$629,AG$9,0) -> 0 | AH26: =VLOOKUP($E26,[1]Sheet1!$E$10:$X$629,AH$9,0) -> 0 | AJ26: =SUM(M26:T26) -> 0 | AK26: =SUM(AA26:AH26) -> 0 | AL26: =IFERROR(AJ26-AK26,0) -> 0
A27: 857494007264 | B27: 2536101 | C27: THE SAHARAN EYESHADOW PALETTE | E27: 1000262 | F27: 021 | G27: 3453 - JUVIA'S PLACE | I27: X | J27: BASC | K27: 10 | L27: 9.99 | M27: 0 | N27: 0 | O27: 0 | P27: 0 | Q27: 0 | R27: 0 | S27: 0 | T27: 0 | U27: 0 | V27: 0 | W27: 0 | X27: 0 | Z27: =VLOOKUP(E27,Sheet2!$A$1:$A$39,1,0) -> #N/A | AA27: =VLOOKUP($E27,[1]Sheet1!$E$10:$X$629,AA$9,0) -> 0 | AB27: =VLOOKUP($E27,[1]Sheet1!$E$10:$X$629,AB$9,0) -> 0 | AC27: =VLOOKUP($E27,[1]Sheet1!$E$10:$X$629,AC$9,0) -> 0 | AD27: =VLOOKUP($E27,[1]Sheet1!$E$10:$X$629,AD$9,0) -> 0 | AE27: =VLOOKUP($E27,[1]Sheet1!$E$10:$X$629,AE$9,0) -> 0 | AF27: =VLOOKUP($E27,[1]Sheet1!$E$10:$X$629,AF$9,0) -> 0 | AG27: =VLOOKUP($E27,[1]Sheet1!$E$10:$X$629,AG$9,0) -> 0 | AH27: =VLOOKUP($E27,[1]Sheet1!$E$10:$X$629,AH$9,0) -> 0 | AJ27: =SUM(M27:T27) -> 0 | AK27: =SUM(AA27:AH27) -> 0 | AL27: =IFERROR(AJ27-AK27,0) -> 0
A28: 869001000217 | B28: 2536102 | C28: THE NUBIAN EYESHADOW PALETTE NUBIAN 2 | E28: 1000098 | F28: 021 | G28: 3453 - JUVIA'S PLACE | H28: F | I28: X | J28: BASC | K28: 10 | L28: 5 | M28: 0 | N28: 0 | O28: 0 | P28: 0 | Q28: 0 | R28: 0 | S28: 0 | T28: 0 | U28: 0 | V28: 0 | W28: 0 | X28: 0 | Z28: =VLOOKUP(E28,Sheet2!$A$1:$A$39,1,0) -> #N/A | AA28: =VLOOKUP($E28,[1]Sheet1!$E$10:$X$629,AA$9,0) -> 0 | AB28: =VLOOKUP($E28,[1]Sheet1!$E$10:$X$629,AB$9,0) -> 0 | AC28: =VLOOKUP($E28,[1]Sheet1!$E$10:$X$629,AC$9,0) -> 0 | AD28: =VLOOKUP($E28,[1]Sheet1!$E$10:$X$629,AD$9,0) -> 0 | AE28: =VLOOKUP($E28,[1]Sheet1!$E$10:$X$629,AE$9,0) -> 0 | AF28: =VLOOKUP($E28,[1]Sheet1!$E$10:$X$629,AF$9,0) -> 0 | AG28: =VLOOKUP($E28,[1]Sheet1!$E$10:$X$629,AG$9,0) -> 0 | AH28: =VLOOKUP($E28,[1]Sheet1!$E$10:$X$629,AH$9,0) -> 0 | AJ28: =SUM(M28:T28) -> 0 | AK28: =SUM(AA28:AH28) -> 0 | AL28: =IFERROR(AJ28-AK28,0) -> 0
A29: 857494007240 | B29: 2536105 | C29: THE ROYALTY GLOW LOOSE HIGHLIGHTER | E29: 1000809 | F29: 021 | G29: 3453 - JUVIA'S PLACE | I29: X | J29: BASC | K29: 7 | L29: 14 | M29: 0 | N29: 0 | O29: 0 | P29: 0 | Q29: 0 | R29: 0 | S29: 0 | T29: 0 | U29: 0 | V29: 0 | W29: 0 | X29: 0 | Z29: =VLOOKUP(E29,Sheet2!$A$1:$A$39,1,0) -> #N/A | AA29: =VLOOKUP($E29,[1]Sheet1!$E$10:$X$629,AA$9,0) -> 0 | AB29: =VLOOKUP($E29,[1]Sheet1!$E$10:$X$629,AB$9,0) -> 0 | AC29: =VLOOKUP($E29,[1]Sheet1!$E$10:$X$629,AC$9,0) -> 0 | AD29: =VLOOKUP($E29,[1]Sheet1!$E$10:$X$629,AD$9,0) -> 0 | AE29: =VLOOKUP($E29,[1]Sheet1!$E$10:$X$629,AE$9,0) -> 0 | AF29: =VLOOKUP($E29,[1]Sheet1!$E$10:$X$629,AF$9,0) -> 0 | AG29: =VLOOKUP($E29,[1]Sheet1!$E$10:$X$629,AG$9,0) -> 0 | AH29: =VLOOKUP($E29,[1]Sheet1!$E$10:$X$629,AH$9,0) -> 0 | AJ29: =SUM(M29:T29) -> 0 | AK29: =SUM(AA29:AH29) -> 0 | AL29: =IFERROR(AJ29-AK29,0) -> 0
A30: 869001000200 | B30: 2536106 | C30: THE NUBIAN EYESHADOW PALETTE NUBIAN 2 | E30: 1000097 | F30: 021 | G30: 3453 - JUVIA'S PLACE | H30: E | I30: A | J30: BASC | K30: 12.5 | L30: 25 | M30: 480 | N30: 576 | O30: 768 | P30: 480 | Q30: 480 | R30: 672 | S30: 576 | T30: 480 | U30: 1056 | V30: 1248 | W30: 576 | X30: 1152 | Z30: =VLOOKUP(E30,Sheet2!$A$1:$A$39,1,0) -> #N/A | AA30: =VLOOKUP($E30,[1]Sheet1!$E$10:$X$629,AA$9,0) -> 480 | AB30: =VLOOKUP($E30,[1]Sheet1!$E$10:$X$629,AB$9,0) -> 672 | AC30: =VLOOKUP($E30,[1]Sheet1!$E$10:$X$629,AC$9,0) -> 672 | AD30: =VLOOKUP($E30,[1]Sheet1!$E$10:$X$629,AD$9,0) -> 576 | AE30: =VLOOKUP($E30,[1]Sheet1!$E$10:$X$629,AE$9,0) -> 672 | AF30: =VLOOKUP($E30,[1]Sheet1!$E$10:$X$629,AF$9,0) -> 480 | AG30: =VLOOKUP($E30,[1]Sheet1!$E$10:$X$629,AG$9,0) -> 672 | AH30: =VLOOKUP($E30,[1]Sheet1!$E$10:$X$629,AH$9,0) -> 192 | AJ30: =SUM(M30:T30) -> 4512 | AK30: =SUM(AA30:AH30) -> 4416 | AL30: =IFERROR(AJ30-AK30,0) -> 96
A31: 857494007431 | B31: 2537042 | C31: THE NUBIAN LOOSE HIGHLIGHTER NERFERTITI | E31: 1000803 | F31: 021 | G31: 3453 - JUVIA'S PLACE | H31: E | I31: A | J31: BASC | K31: 7.5 | L31: 15 | M31: 576 | N31: 1008 | O31: 720 | P31: 720 | Q31: 576 | R31: 1008 | S31: 576 | T31: 864 | U31: 720 | V31: 1152 | W31: 1008 | X31: 720 | Z31: =VLOOKUP(E31,Sheet2!$A$1:$A$39,1,0) -> #N/A | AA31: =VLOOKUP($E31,[1]Sheet1!$E$10:$X$629,AA$9,0) -> 432 | AB31: =VLOOKUP($E31,[1]Sheet1!$E$10:$X$629,AB$9,0) -> 576 | AC31: =VLOOKUP($E31,[1]Sheet1!$E$10:$X$629,AC$9,0) -> 864 | AD31: =VLOOKUP($E31,[1]Sheet1!$E$10:$X$629,AD$9,0) -> 432 | AE31: =VLOOKUP($E31,[1]Sheet1!$E$10:$X$629,AE$9,0) -> 432 | AF31: =VLOOKUP($E31,[1]Sheet1!$E$10:$X$629,AF$9,0) -> 720 | AG31: =VLOOKUP($E31,[1]Sheet1!$E$10:$X$629,AG$9,0) -> 576 | AH31: =VLOOKUP($E31,[1]Sheet1!$E$10:$X$629,AH$9,0) -> 144 | AJ31: =SUM(M31:T31) -> 6048 | AK31: =SUM(AA31:AH31) -> 4176 | AL31: =IFERROR(AJ31-AK31,0) -> 1872
A32: 857494007424 | B32: 2537043 | C32: THE NUBIAN LOOSE HIGHLIGHTER NUBIA | E32: 1000806 | F32: 021 | G32: 3453 - JUVIA'S PLACE | I32: X | J32: BASC | K32: 7 | L32: 14 | M32: 0 | N32: 0 | O32: 0 | P32: 0 | Q32: 0 | R32: 0 | S32: 0 | T32: 0 | U32: 0 | V32: 0 | W32: 0 | X32: 0 | Z32: =VLOOKUP(E32,Sheet2!$A$1:$A$39,1,0) -> #N/A | AA32: =VLOOKUP($E32,[1]Sheet1!$E$10:$X$629,AA$9,0) -> 0 | AB32: =VLOOKUP($E32,[1]Sheet1!$E$10:$X$629,AB$9,0) -> 0 | AC32: =VLOOKUP($E32,[1]Sheet1!$E$10:$X$629,AC$9,0) -> 0 | AD32: =VLOOKUP($E32,[1]Sheet1!$E$10:$X$629,AD$9,0) -> 0 | AE32: =VLOOKUP($E32,[1]Sheet1!$E$10:$X$629,AE$9,0) -> 0 | AF32: =VLOOKUP($E32,[1]Sheet1!$E$10:$X$629,AF$9,0) -> 0 | AG32: =VLOOKUP($E32,[1]Sheet1!$E$10:$X$629,AG$9,0) -> 0 | AH32: =VLOOKUP($E32,[1]Sheet1!$E$10:$X$629,AH$9,0) -> 0 | AJ32: =SUM(M32:T32) -> 0 | AK32: =SUM(AA32:AH32) -> 0 | AL32: =IFERROR(AJ32-AK32,0) -> 0
A33: 857494007479 | B33: 2537070 | C33: THE NUBIAN EYESHADOW PALETTE NUBIAN 3 | E33: 1000351 | F33: 021 | G33: 3453 - JUVIA'S PLACE | H33: F | I33: DI | J33: BASC | K33: 10 | L33: 20 | M33: 0 | N33: 0 | O33: 0 | P33: 0 | Q33: 0 | R33: 0 | S33: 0 | T33: 0 | U33: 0 | V33: 0 | W33: 0 | X33: 0 | Z33: =VLOOKUP(E33,Sheet2!$A$1:$A$39,1,0) -> #N/A | AA33: =VLOOKUP($E33,[1]Sheet1!$E$10:$X$629,AA$9,0) -> 0 | AB33: =VLOOKUP($E33,[1]Sheet1!$E$10:$X$629,AB$9,0) -> 0 | AC33: =VLOOKUP($E33,[1]Sheet1!$E$10:$X$629,AC$9,0) -> 0 | AD33: =VLOOKUP($E33,[1]Sheet1!$E$10:$X$629,AD$9,0) -> 0 | AE33: =VLOOKUP($E33,[1]Sheet1!$E$10:$X$629,AE$9,0) -> 0 | AF33: =VLOOKUP($E33,[1]Sheet1!$E$10:$X$629,AF$9,0) -> 0 | AG33: =VLOOKUP($E33,[1]Sheet1!$E$10:$X$629,AG$9,0) -> 0 | AH33: =VLOOKUP($E33,[1]Sheet1!$E$10:$X$629,AH$9,0) -> 0 | AJ33: =SUM(M33:T33) -> 0 | AK33: =SUM(AA33:AH33) -> 0 | AL33: =IFERROR(AJ33-AK33,0) -> 0
A34: 857494007110 | B34: 2546937 | C34: THE NUBIAN LOOSE HIGHLIGHTER | E34: 1000800 | F34: 021 | G34: 3453 - JUVIA'S PLACE | H34: C | I34: X | J34: BASC | K34: 7 | L34: 14 | M34: 0 | N34: 0 | O34: 0 | P34: 0 | Q34: 0 | R34: 0 | S34: 0 | T34: 0 | U34: 0 | V34: 0 | W34: 0 | X34: 0 | Z34: =VLOOKUP(E34,Sheet2!$A$1:$A$39,1,0) -> #N/A | AA34: =VLOOKUP($E34,[1]Sheet1!$E$10:$X$629,AA$9,0) -> 0 | AB34: =VLOOKUP($E34,[1]Sheet1!$E$10:$X$629,AB$9,0) -> 0 | AC34: =VLOOKUP($E34,[1]Sheet1!$E$10:$X$629,AC$9,0) -> 0 | AD34: =VLOOKUP($E34,[1]Sheet1!$E$10:$X$629,AD$9,0) -> 0 | AE34: =VLOOKUP($E34,[1]Sheet1!$E$10:$X$629,AE$9,0) -> 0 | AF34: =VLOOKUP($E34,[1]Sheet1!$E$10:$X$629,AF$9,0) -> 0 | AG34: =VLOOKUP($E34,[1]Sheet1!$E$10:$X$629,AG$9,0) -> 0 | AH34: =VLOOKUP($E34,[1]Sheet1!$E$10:$X$629,AH$9,0) -> 0 | AJ34: =SUM(M34:T34) -> 0 | AK34: =SUM(AA34:AH34) -> 0 | AL34: =IFERROR(AJ34-AK34,0) -> 0
A35: 857494007219 | B35: 2547089 | C35: THE NUBIAN EYESHADOW PALETTE NUBIAN MINI | E35: 1000100 | F35: 021 | G35: 3453 - JUVIA'S PLACE | I35: DI | J35: BASC | K35: 5 | L35: 5 | M35: 0 | N35: 0 | O35: 0 | P35: 0 | Q35: 0 | R35: 0 | S35: 0 | T35: 0 | U35: 0 | V35: 0 | W35: 0 | X35: 0 | Z35: =VLOOKUP(E35,Sheet2!$A$1:$A$39,1,0) -> #N/A | AA35: =VLOOKUP($E35,[1]Sheet1!$E$10:$X$629,AA$9,0) -> 0 | AB35: =VLOOKUP($E35,[1]Sheet1!$E$10:$X$629,AB$9,0) -> 0 | AC35: =VLOOKUP($E35,[1]Sheet1!$E$10:$X$629,AC$9,0) -> 0 | AD35: =VLOOKUP($E35,[1]Sheet1!$E$10:$X$629,AD$9,0) -> 0 | AE35: =VLOOKUP($E35,[1]Sheet1!$E$10:$X$629,AE$9,0) -> 0 | AF35: =VLOOKUP($E35,[1]Sheet1!$E$10:$X$629,AF$9,0) -> 0 | AG35: =VLOOKUP($E35,[1]Sheet1!$E$10:$X$629,AG$9,0) -> 0 | AH35: =VLOOKUP($E35,[1]Sheet1!$E$10:$X$629,AH$9,0) -> 0 | AJ35: =SUM(M35:T35) -> 0 | AK35: =SUM(AA35:AH35) -> 0 | AL35: =IFERROR(AJ35-AK35,0) -> 0
A36: 857494007127 | B36: 2547607 | C36: THE HEROINE LOOSE HIGHLIGHTER | E36: 4007127 | F36: 021 | G36: 3453 - JUVIA'S PLACE | I36: X | J36: BASC | K36: 7 | L36: 6.99 | M36: 0 | N36: 0 | O36: 0 | P36: 0 | Q36: 0 | R36: 0 | S36: 0 | T36: 0 | U36: 0 | V36: 0 | W36: 0 | X36: 0 | Z36: =VLOOKUP(E36,Sheet2!$A$1:$A$39,1,0) -> #N/A | AA36: =VLOOKUP($E36,[1]Sheet1!$E$10:$X$629,AA$9,0) -> 0 | AB36: =VLOOKUP($E36,[1]Sheet1!$E$10:$X$629,AB$9,0) -> 0 | AC36: =VLOOKUP($E36,[1]Sheet1!$E$10:$X$629,AC$9,0) -> 0 | AD36: =VLOOKUP($E36,[1]Sheet1!$E$10:$X$629,AD$9,0) -> 0 | AE36: =VLOOKUP($E36,[1]Sheet1!$E$10:$X$629,AE$9,0) -> 0 | AF36: =VLOOKUP($E36,[1]Sheet1!$E$10:$X$629,AF$9,0) -> 0 | AG36: =VLOOKUP($E36,[1]Sheet1!$E$10:$X$629,AG$9,0) -> 0 | AH36: =VLOOKUP($E36,[1]Sheet1!$E$10:$X$629,AH$9,0) -> 0 | AJ36: =SUM(M36:T36) -> 0 | AK36: =SUM(AA36:AH36) -> 0 | AL36: =IFERROR(AJ36-AK36,0) -> 0
A37: 857494007103 | B37: 2547799 | C37: THE TRIBE HIGHLIGHTER | E37: 1000372 | F37: 021 | G37: 3453 - JUVIA'S PLACE | H37: C | I37: DI | J37: BASC | K37: 6 | L37: 1.2 | M37: 0 | N37: 0 | O37: 0 | P37: 0 | Q37: 0 | R37: 0 | S37: 0 | T37: 0 | U37: 0 | V37: 0 | W37: 0 | X37: 0 | Z37: =VLOOKUP(E37,Sheet2!$A$1:$A$39,1,0) -> #N/A | AA37: =VLOOKUP($E37,[1]Sheet1!$E$10:$X$629,AA$9,0) -> 0 | AB37: =VLOOKUP($E37,[1]Sheet1!$E$10:$X$629,AB$9,0) -> 0 | AC37: =VLOOKUP($E37,[1]Sheet1!$E$10:$X$629,AC$9,0) -> 0 | AD37: =VLOOKUP($E37,[1]Sheet1!$E$10:$X$629,AD$9,0) -> 0 | AE37: =VLOOKUP($E37,[1]Sheet1!$E$10:$X$629,AE$9,0) -> 0 | AF37: =VLOOKUP($E37,[1]Sheet1!$E$10:$X$629,AF$9,0) -> 0 | AG37: =VLOOKUP($E37,[1]Sheet1!$E$10:$X$629,AG$9,0) -> 0 | AH37: =VLOOKUP($E37,[1]Sheet1!$E$10:$X$629,AH$9,0) -> 0 | AJ37: =SUM(M37:T37) -> 0 | AK37: =SUM(AA37:AH37) -> 0 | AL37: =IFERROR(AJ37-AK37,0) -> 0
A38: 810018870010 | B38: 2550477 | C38: I AM MAGIC FOUNDATION 110 SENEGAL | E38: 1000112 | F38: 021 | G38: 3453 - JUVIA'S PLACE | I38: A | J38: BASC | K38: 14.4 | L38: 20 | M38: 0 | N38: 0 | O38: 0 | P38: 0 | Q38: 0 | R38: 0 | S38: 0 | T38: 0 | U38: 0 | V38: 0 | W38: 0 | X38: 0 | Z38: =VLOOKUP(E38,Sheet2!$A$1:$A$39,1,0) -> #N/A | AA38: =VLOOKUP($E38,[1]Sheet1!$E$10:$X$629,AA$9,0) -> 0 | AB38: =VLOOKUP($E38,[1]Sheet1!$E$10:$X$629,AB$9,0) -> 0 | AC38: =VLOOKUP($E38,[1]Sheet1!$E$10:$X$629,AC$9,0) -> 0 | AD38: =VLOOKUP($E38,[1]Sheet1!$E$10:$X$629,AD$9,0) -> 0 | AE38: =VLOOKUP($E38,[1]Sheet1!$E$10:$X$629,AE$9,0) -> 0 | AF38: =VLOOKUP($E38,[1]Sheet1!$E$10:$X$629,AF$9,0) -> 0 | AG38: =VLOOKUP($E38,[1]Sheet1!$E$10:$X$629,AG$9,0) -> 0 | AH38: =VLOOKUP($E38,[1]Sheet1!$E$10:$X$629,AH$9,0) -> 0 | AJ38: =SUM(M38:T38) -> 0 | AK38: =SUM(AA38:AH38) -> 0 | AL38: =IFERROR(AJ38-AK38,0) -> 0
A39: 810018870034 | B39: 2550478 | C39: I AM MAGIC FOUNDATION 130 MALI | E39: 1000114 | F39: 021 | G39: 3453 - JUVIA'S PLACE | H39: F | I39: A | J39: BASC | K39: 14.4 | L39: 20 | M39: 90 | N39: 90 | O39: 90 | P39: 0 | Q39: 0 | R39: 90 | S39: 90 | T39: 0 | U39: 180 | V39: 0 | W39: 90 | X39: 0 | Z39: =VLOOKUP(E39,Sheet2!$A$1:$A$39,1,0) -> #N/A | AA39: =VLOOKUP($E39,[1]Sheet1!$E$10:$X$629,AA$9,0) -> 90 | AB39: =VLOOKUP($E39,[1]Sheet1!$E$10:$X$629,AB$9,0) -> 180 | AC39: =VLOOKUP($E39,[1]Sheet1!$E$10:$X$629,AC$9,0) -> 180 | AD39: =VLOOKUP($E39,[1]Sheet1!$E$10:$X$629,AD$9,0) -> 180 | AE39: =VLOOKUP($E39,[1]Sheet1!$E$10:$X$629,AE$9,0) -> 0 | AF39: =VLOOKUP($E39,[1]Sheet1!$E$10:$X$629,AF$9,0) -> 270 | AG39: =VLOOKUP($E39,[1]Sheet1!$E$10:$X$629,AG$9,0) -> 180 | AH39: =VLOOKUP($E39,[1]Sheet1!$E$10:$X$629,AH$9,0) -> 0 | AJ39: =SUM(M39:T39) -> 450 | AK39: =SUM(AA39:AH39) -> 1080 | AL39: =IFERROR(AJ39-AK39,0) -> -630
A40: 810018870003 | B40: 2550479 | C40: I AM MAGIC FOUNDATION 100 SUDAN | E40: 1000111 | F40: 021 | G40: 3453 - JUVIA'S PLACE | I40: A | J40: BASC | K40: 14.4 | L40: 20 | M40: 0 | N40: 0 | O40: 0 | P40: 0 | Q40: 0 | R40: 0 | S40: 0 | T40: 0 | U40: 0 | V40: 0 | W40: 0 | X40: 0 | Z40: =VLOOKUP(E40,Sheet2!$A$1:$A$39,1,0) -> #N/A | AA40: =VLOOKUP($E40,[1]Sheet1!$E$10:$X$629,AA$9,0) -> 0 | AB40: =VLOOKUP($E40,[1]Sheet1!$E$10:$X$629,AB$9,0) -> 0 | AC40: =VLOOKUP($E40,[1]Sheet1!$E$10:$X$629,AC$9,0) -> 0 | AD40: =VLOOKUP($E40,[1]Sheet1!$E$10:$X$629,AD$9,0) -> 0 | AE40: =VLOOKUP($E40,[1]Sheet1!$E$10:$X$629,AE$9,0) -> 0 | AF40: =VLOOKUP($E40,[1]Sheet1!$E$10:$X$629,AF$9,0) -> 0 | AG40: =VLOOKUP($E40,[1]Sheet1!$E$10:$X$629,AG$9,0) -> 0 | AH40: =VLOOKUP($E40,[1]Sheet1!$E$10:$X$629,AH$9,0) -> 0 | AJ40: =SUM(M40:T40) -> 0 | AK40: =SUM(AA40:AH40) -> 0 | AL40: =IFERROR(AJ40-AK40,0) -> 0
A41: 810018870027 | B41: 2550480 | C41: I AM MAGIC FOUNDATION 120 CHAD | E41: 1000113 | F41: 021 | G41: 3453 - JUVIA'S PLACE | H41: F | I41: A | J41: BASC | K41: 14.4 | L41: 20 | M41: 90 | N41: 0 | O41: 0 | P41: 90 | Q41: 0 | R41: 0 | S41: 90 | T41: 180 | U41: 0 | V41: 90 | W41: 90 | X41: 90 | Z41: =VLOOKUP(E41,Sheet2!$A$1:$A$39,1,0) -> #N/A | AA41: =VLOOKUP($E41,[1]Sheet1!$E$10:$X$629,AA$9,0) -> 90 | AB41: =VLOOKUP($E41,[1]Sheet1!$E$10:$X$629,AB$9,0) -> 180 | AC41: =VLOOKUP($E41,[1]Sheet1!$E$10:$X$629,AC$9,0) -> 90 | AD41: =VLOOKUP($E41,[1]Sheet1!$E$10:$X$629,AD$9,0) -> 90 | AE41: =VLOOKUP($E41,[1]Sheet1!$E$10:$X$629,AE$9,0) -> 90 | AF41: =VLOOKUP($E41,[1]Sheet1!$E$10:$X$629,AF$9,0) -> 90 | AG41: =VLOOKUP($E41,[1]Sheet1!$E$10:$X$629,AG$9,0) -> 90 | AH41: =VLOOKUP($E41,[1]Sheet1!$E$10:$X$629,AH$9,0) -> 90 | AJ41: =SUM(M41:T41) -> 450 | AK41: =SUM(AA41:AH41) -> 810 | AL41: =IFERROR(AJ41-AK41,0) -> -360
A42: 810018870072 | B42: 2550481 | C42: I AM MAGIC FOUNDATION 205 TANZANIA | E42: 1000118 | F42: 021 | G42: 3453 - JUVIA'S PLACE | H42: F | I42: A | J42: BASC | K42: 14.4 | L42: 20 | M42: 0 | N42: 360 | O42: 90 | P42: 90 | Q42: 270 | R42: 90 | S42: 90 | T42: 270 | U42: 90 | V42: 180 | W42: 270 | X42: 90 | Z42: =VLOOKUP(E42,Sheet2!$A$1:$A$39,1,0) -> #N/A | AA42: =VLOOKUP($E42,[1]Sheet1!$E$10:$X$629,AA$9,0) -> 360 | AB42: =VLOOKUP($E42,[1]Sheet1!$E$10:$X$629,AB$9,0) -> 270 | AC42: =VLOOKUP($E42,[1]Sheet1!$E$10:$X$629,AC$9,0) -> 270 | AD42: =VLOOKUP($E42,[1]Sheet1!$E$10:$X$629,AD$9,0) -> 360 | AE42: =VLOOKUP($E42,[1]Sheet1!$E$10:$X$629,AE$9,0) -> 180 | AF42: =VLOOKUP($E42,[1]Sheet1!$E$10:$X$629,AF$9,0) -> 450 | AG42: =VLOOKUP($E42,[1]Sheet1!$E$10:$X$629,AG$9,0) -> 180 | AH42: =VLOOKUP($E42,[1]Sheet1!$E$10:$X$629,AH$9,0) -> 270 | AJ42: =SUM(M42:T42) -> 1260 | AK42: =SUM(AA42:AH42) -> 2340 | AL42: =IFERROR(AJ42-AK42,0) -> -1080
A43: 810018870065 | B43: 2550482 | C43: I AM MAGIC FOUNDATION 200 KENYA | E43: 1000117 | F43: 021 | G43: 3453 - JUVIA'S PLACE | H43: F | I43: A | J43: BASC | K43: 14.4 | L43: 20 | M43: 270 | N43: 90 | O43: 90 | P43: 0 | Q43: 90 | R43: 180 | S43: 180 | T43: 0 | U43: 180 | V43: 0 | W43: 270 | X43: 0 | Z43: =VLOOKUP(E43,Sheet2!$A$1:$A$39,1,0) -> #N/A | AA43: =VLOOKUP($E43,[1]Sheet1!$E$10:$X$629,AA$9,0) -> 0 | AB43: =VLOOKUP($E43,[1]Sheet1!$E$10:$X$629,AB$9,0) -> 180 | AC43: =VLOOKUP($E43,[1]Sheet1!$E$10:$X$629,AC$9,0) -> 360 | AD43: =VLOOKUP($E43,[1]Sheet1!$E$10:$X$629,AD$9,0) -> 90 | AE43: =VLOOKUP($E43,[1]Sheet1!$E$10:$X$629,AE$9,0) -> 90 | AF43: =VLOOKUP($E43,[1]Sheet1!$E$10:$X$629,AF$9,0) -> 180 | AG43: =VLOOKUP($E43,[1]Sheet1!$E$10:$X$629,AG$9,0) -> 270 | AH43: =VLOOKUP($E43,[1]Sheet1!$E$10:$X$629,AH$9,0) -> 0 | AJ43: =SUM(M43:T43) -> 900 | AK43: =SUM(AA43:AH43) -> 1170 | AL43: =IFERROR(AJ43-AK43,0) -> -270
A44: 810018870089 | B44: 2550483 | C44: I AM MAGIC FOUNDATION 210 TOGO | E44: 1000119 | F44: 021 | G44: 3453 - JUVIA'S PLACE | H44: F | I44: A | J44: BASC | K44: 14.4 | L44: 20 | M44: 0 | N44: 180 | O44: 90 | P44: 180 | Q44: 0 | R44: 180 | S44: 180 | T44: 90 | U44: 90 | V44: 270 | W44: 90 | X44: 90 | Z44: =VLOOKUP(E44,Sheet2!$A$1:$A$39,1,0) -> #N/A | AA44: =VLOOKUP($E44,[1]Sheet1!$E$10:$X$629,AA$9,0) -> 270 | AB44: =VLOOKUP($E44,[1]Sheet1!$E$10:$X$629,AB$9,0) -> 180 | AC44: =VLOOKUP($E44,[1]Sheet1!$E$10:$X$629,AC$9,0) -> 360 | AD44: =VLOOKUP($E44,[1]Sheet1!$E$10:$X$629,AD$9,0) -> 270 | AE44: =VLOOKUP($E44,[1]Sheet1!$E$10:$X$629,AE$9,0) -> 90 | AF44: =VLOOKUP($E44,[1]Sheet1!$E$10:$X$629,AF$9,0) -> 450 | AG44: =VLOOKUP($E44,[1]Sheet1!$E$10:$X$629,AG$9,0) -> 180 | AH44: =VLOOKUP($E44,[1]Sheet1!$E$10:$X$629,AH$9,0) -> 270 | AJ44: =SUM(M44:T44) -> 900 | AK44: =SUM(AA44:AH44) -> 2070 | AL44: =IFERROR(AJ44-AK44,0) -> -1170
A45: 810018870058 | B45: 2550484 | C45: I AM MAGIC FOUNDATION 150 KANO | E45: 1000116 | F45: 021 | G45: 3453 - JUVIA'S PLACE | H45: F | I45: A | J45: BASC | K45: 14.4 | L45: 20 | M45: 0 | N45: 90 | O45: 180 | P45: 90 | Q45: 180 | R45: 0 | S45: 270 | T45: 90 | U45: 180 | V45: 180 | W45: 90 | X45: 90 | Z45: =VLOOKUP(E45,Sheet2!$A$1:$A$39,1,0) -> #N/A | AA45: =VLOOKUP($E45,[1]Sheet1!$E$10:$X$629,AA$9,0) -> 270 | AB45: =VLOOKUP($E45,[1]Sheet1!$E$10:$X$629,AB$9,0) -> 180 | AC45: =VLOOKUP($E45,[1]Sheet1!$E$10:$X$629,AC$9,0) -> 270 | AD45: =VLOOKUP($E45,[1]Sheet1!$E$10:$X$629,AD$9,0) -> 270 | AE45: =VLOOKUP($E45,[1]Sheet1!$E$10:$X$629,AE$9,0) -> 90 | AF45: =VLOOKUP($E45,[1]Sheet1!$E$10:$X$629,AF$9,0) -> 270 | AG45: =VLOOKUP($E45,[1]Sheet1!$E$10:$X$629,AG$9,0) -> 360 | AH45: =VLOOKUP($E45,[1]Sheet1!$E$10:$X$629,AH$9,0) -> 0 | AJ45: =SUM(M45:T45) -> 900 | AK45: =SUM(AA45:AH45) -> 1710 | AL45: =IFERROR(AJ45-AK45,0) -> -810
A46: 810018870041 | B46: 2550485 | C46: I AM MAGIC FOUNDATION 140 ANGOLA | E46: 1000115 | F46: 021 | G46: 3453 - JUVIA'S PLACE | H46: F | I46: A | J46: BASC | K46: 14.4 | L46: 20 | M46: 90 | N46: 180 | O46: 90 | P46: 270 | Q46: 0 | R46: 180 | S46: 270 | T46: 180 | U46: 90 | V46: 180 | W46: 270 | X46: 180 | Z46: =VLOOKUP(E46,Sheet2!$A$1:$A$39,1,0) -> #N/A | AA46: =VLOOKUP($E46,[1]Sheet1!$E$10:$X$629,AA$9,0) -> 270 | AB46: =VLOOKUP($E46,[1]Sheet1!$E$10:$X$629,AB$9,0) -> 90 | AC46: =VLOOKUP($E46,[1]Sheet1!$E$10:$X$629,AC$9,0) -> 450 | AD46: =VLOOKUP($E46,[1]Sheet1!$E$10:$X$629,AD$9,0) -> 90 | AE46: =VLOOKUP($E46,[1]Sheet1!$E$10:$X$629,AE$9,0) -> 360 | AF46: =VLOOKUP($E46,[1]Sheet1!$E$10:$X$629,AF$9,0) -> 270 | AG46: =VLOOKUP($E46,[1]Sheet1!$E$10:$X$629,AG$9,0) -> 360 | AH46: =VLOOKUP($E46,[1]Sheet1!$E$10:$X$629,AH$9,0) -> 0 | AJ46: =SUM(M46:T46) -> 1260 | AK46: =SUM(AA46:AH46) -> 1890 | AL46: =IFERROR(AJ46-AK46,0) -> -630
A47: 810018870164 | B47: 2550486 | C47: I AM MAGIC FOUNDATION 340 KAMPALA | E47: 1000127 | F47: 021 | G47: 3453 - JUVIA'S PLACE | H47: F | I47: A | J47: BASC | K47: 14.4 | L47: 20 | M47: 180 | N47: 360 | O47: 270 | P47: 360 | Q47: 0 | R47: 450 | S47: 270 | T47: 270 | U47: 270 | V47: 270 | W47: 180 | X47: 450 | Z47: =VLOOKUP(E47,Sheet2!$A$1:$A$39,1,0) -> #N/A | AA47: =VLOOKUP($E47,[1]Sheet1!$E$10:$X$629,AA$9,0) -> 360 | AB47: =VLOOKUP($E47,[1]Sheet1!$E$10:$X$629,AB$9,0) -> 270 | AC47: =VLOOKUP($E47,[1]Sheet1!$E$10:$X$629,AC$9,0) -> 450 | AD47: =VLOOKUP($E47,[1]Sheet1!$E$10:$X$629,AD$9,0) -> 450 | AE47: =VLOOKUP($E47,[1]Sheet1!$E$10:$X$629,AE$9,0) -> 360 | AF47: =VLOOKUP($E47,[1]Sheet1!$E$10:$X$629,AF$9,0) -> 450 | AG47: =VLOOKUP($E47,[1]Sheet1!$E$10:$X$629,AG$9,0) -> 360 | AH47: =VLOOKUP($E47,[1]Sheet1!$E$10:$X$629,AH$9,0) -> 270 | AJ47: =SUM(M47:T47) -> 2160 | AK47: =SUM(AA47:AH47) -> 2970 | AL47: =IFERROR(AJ47-AK47,0) -> -810
A48: 810018870171 | B48: 2550487 | C48: I AM MAGIC FOUNDATION 350 SOMALIA | E48: 1000128 | F48: 021 | G48: 3453 - JUVIA'S PLACE | H48: F | I48: A | J48: BASC | K48: 14.4 | L48: 20 | M48: 90 | N48: 90 | O48: 180 | P48: 180 | Q48: 90 | R48: 180 | S48: 90 | T48: 90 | U48: 270 | V48: 0 | W48: 270 | X48: 180 | Z48: =VLOOKUP(E48,Sheet2!$A$1:$A$39,1,0) -> #N/A | AA48: =VLOOKUP($E48,[1]Sheet1!$E$10:$X$629,AA$9,0) -> 180 | AB48: =VLOOKUP($E48,[1]Sheet1!$E$10:$X$629,AB$9,0) -> 270 | AC48: =VLOOKUP($E48,[1]Sheet1!$E$10:$X$629,AC$9,0) -> 270 | AD48: =VLOOKUP($E48,[1]Sheet1!$E$10:$X$629,AD$9,0) -> 270 | AE48: =VLOOKUP($E48,[1]Sheet1!$E$10:$X$629,AE$9,0) -> 360 | AF48: =VLOOKUP($E48,[1]Sheet1!$E$10:$X$629,AF$9,0) -> 180 | AG48: =VLOOKUP($E48,[1]Sheet1!$E$10:$X$629,AG$9,0) -> 360 | AH48: =VLOOKUP($E48,[1]Sheet1!$E$10:$X$629,AH$9,0) -> 90 | AJ48: =SUM(M48:T48) -> 990 | AK48: =SUM(AA48:AH48) -> 1980 | AL48: =IFERROR(AJ48-AK48,0) -> -990
A49: 810018870287 | B49: 2550488 | C49: I AM MAGIC FOUNDATION 530 IBIZA | E49: 1000139 | F49: 021 | G49: 3453 - JUVIA'S PLACE | H49: F | I49: A | J49: BASC | K49: 14.4 | L49: 20 | M49: 270 | N49: 180 | O49: 270 | P49: 180 | Q49: 270 | R49: 360 | S49: 180 | T49: 180 | U49: 360 | V49: 270 | W49: 270 | X49: 270 | Z49: =VLOOKUP(E49,Sheet2!$A$1:$A$39,1,0) -> #N/A | AA49: =VLOOKUP($E49,[1]Sheet1!$E$10:$X$629,AA$9,0) -> 270 | AB49: =VLOOKUP($E49,[1]Sheet1!$E$10:$X$629,AB$9,0) -> 360 | AC49: =VLOOKUP($E49,[1]Sheet1!$E$10:$X$629,AC$9,0) -> 360 | AD49: =VLOOKUP($E49,[1]Sheet1!$E$10:$X$629,AD$9,0) -> 360 | AE49: =VLOOKUP($E49,[1]Sheet1!$E$10:$X$629,AE$9,0) -> 360 | AF49: =VLOOKUP($E49,[1]Sheet1!$E$10:$X$629,AF$9,0) -> 360 | AG49: =VLOOKUP($E49,[1]Sheet1!$E$10:$X$629,AG$9,0) -> 360 | AH49: =VLOOKUP($E49,[1]Sheet1!$E$10:$X$629,AH$9,0) -> 90 | AJ49: =SUM(M49:T49) -> 1890 | AK49: =SUM(AA49:AH49) -> 2520 | AL49: =IFERROR(AJ49-AK49,0) -> -630
A50: 810018870096 | B50: 2550489 | C50: I AM MAGIC FOUNDATION 110 SENEGAL | E50: 1000120 | F50: 021 | G50: 3453 - JUVIA'S PLACE | I50: A | J50: BASC | K50: 14.4 | L50: 20 | M50: 0 | N50: 0 | O50: 0 | P50: 0 | Q50: 0 | R50: 0 | S50: 0 | T50: 0 | U50: 0 | V50: 0 | W50: 0 | X50: 0 | Z50: =VLOOKUP(E50,Sheet2!$A$1:$A$39,1,0) -> #N/A | AA50: =VLOOKUP($E50,[1]Sheet1!$E$10:$X$629,AA$9,0) -> 0 | AB50: =VLOOKUP($E50,[1]Sheet1!$E$10:$X$629,AB$9,0) -> 0 | AC50: =VLOOKUP($E50,[1]Sheet1!$E$10:$X$629,AC$9,0) -> 0 | AD50: =VLOOKUP($E50,[1]Sheet1!$E$10:$X$629,AD$9,0) -> 0 | AE50: =VLOOKUP($E50,[1]Sheet1!$E$10:$X$629,AE$9,0) -> 0 | AF50: =VLOOKUP($E50,[1]Sheet1!$E$10:$X$629,AF$9,0) -> 0 | AG50: =VLOOKUP($E50,[1]Sheet1!$E$10:$X$629,AG$9,0) -> 0 | AH50: =VLOOKUP($E50,[1]Sheet1!$E$10:$X$629,AH$9,0) -> 0 | AJ50: =SUM(M50:T50) -> 0 | AK50: =SUM(AA50:AH50) -> 0 | AL50: =IFERROR(AJ50-AK50,0) -> 0
A51: 810018870102 | B51: 2550490 | C51: I AM MAGIC FOUNDATION 230 MALAWI | E51: 1000121 | F51: 021 | G51: 3453 - JUVIA'S PLACE | H51: F | I51: A | J51: BASC | K51: 14.4 | L51: 20 | M51: 90 | N51: 270 | O51: 180 | P51: 90 | Q51: 180 | R51: 270 | S51: 180 | T51: 90 | U51: 360 | V51: 90 | W51: 270 | X51: 270 | Z51: =VLOOKUP(E51,Sheet2!$A$1:$A$39,1,0) -> #N/A | AA51: =VLOOKUP($E51,[1]Sheet1!$E$10:$X$629,AA$9,0) -> 180 | AB51: =VLOOKUP($E51,[1]Sheet1!$E$10:$X$629,AB$9,0) -> 270 | AC51: =VLOOKUP($E51,[1]Sheet1!$E$10:$X$629,AC$9,0) -> 450 | AD51: =VLOOKUP($E51,[1]Sheet1!$E$10:$X$629,AD$9,0) -> 360 | AE51: =VLOOKUP($E51,[1]Sheet1!$E$10:$X$629,AE$9,0) -> 180 | AF51: =VLOOKUP($E51,[1]Sheet1!$E$10:$X$629,AF$9,0) -> 450 | AG51: =VLOOKUP($E51,[1]Sheet1!$E$10:$X$629,AG$9,0) -> 180 | AH51: =VLOOKUP($E51,[1]Sheet1!$E$10:$X$629,AH$9,0) -> 90 | AJ51: =SUM(M51:T51) -> 1350 | AK51: =SUM(AA51:AH51) -> 2160 | AL51: =IFERROR(AJ51-AK51,0) -> -810
A52: 810018870218 | B52: 2550491 | C52: I AM MAGIC FOUNDATION 430 RIO | E52: 1000132 | F52: 021 | G52: 3453 - JUVIA'S PLACE | H52: F | I52: A | J52: BASC | K52: 14.4 | L52: 20 | M52: 0 | N52: 180 | O52: 90 | P52: 90 | Q52: 180 | R52: 90 | S52: 0 | T52: 180 | U52: 90 | V52: 180 | W52: 90 | X52: 180 | Z52: =VLOOKUP(E52,Sheet2!$A$1:$A$39,1,0) -> #N/A | AA52: =VLOOKUP($E52,[1]Sheet1!$E$10:$X$629,AA$9,0) -> 180 | AB52: =VLOOKUP($E52,[1]Sheet1!$E$10:$X$629,AB$9,0) -> 180 | AC52: =VLOOKUP($E52,[1]Sheet1!$E$10:$X$629,AC$9,0) -> 360 | AD52: =VLOOKUP($E52,[1]Sheet1!$E$10:$X$629,AD$9,0) -> 180 | AE52: =VLOOKUP($E52,[1]Sheet1!$E$10:$X$629,AE$9,0) -> 180 | AF52: =VLOOKUP($E52,[1]Sheet1!$E$10:$X$629,AF$9,0) -> 270 | AG52: =VLOOKUP($E52,[1]Sheet1!$E$10:$X$629,AG$9,0) -> 270 | AH52: =VLOOKUP($E52,[1]Sheet1!$E$10:$X$629,AH$9,0) -> 90 | AJ52: =SUM(M52:T52) -> 810 | AK52: =SUM(AA52:AH52) -> 1710 | AL52: =IFERROR(AJ52-AK52,0) -> -900
A53: 810018870300 | B53: 2550492 | C53: I AM MAGIC FOUNDATION 550 MARTINIQUE | E53: 1000141 | F53: 021 | G53: 3453 - JUVIA'S PLACE | H53: F | I53: A | J53: BASC | K53: 14.4 | L53: 20 | M53: 180 | N53: 90 | O53: 270 | P53: 270 | Q53: 180 | R53: 180 | S53: 180 | T53: 270 | U53: 90 | V53: 270 | W53: 360 | X53: 90 | Z53: =VLOOKUP(E53,Sheet2!$A$1:$A$39,1,0) -> #N/A | AA53: =VLOOKUP($E53,[1]Sheet1!$E$10:$X$629,AA$9,0) -> 270 | AB53: =VLOOKUP($E53,[1]Sheet1!$E$10:$X$629,AB$9,0) -> 180 | AC53: =VLOOKUP($E53,[1]Sheet1!$E$10:$X$629,AC$9,0) -> 360 | AD53: =VLOOKUP($E53,[1]Sheet1!$E$10:$X$629,AD$9,0) -> 270 | AE53: =VLOOKUP($E53,[1]Sheet1!$E$10:$X$629,AE$9,0) -> 270 | AF53: =VLOOKUP($E53,[1]Sheet1!$E$10:$X$629,AF$9,0) -> 450 | AG53: =VLOOKUP($E53,[1]Sheet1!$E$10:$X$629,AG$9,0) -> 270 | AH53: =VLOOKUP($E53,[1]Sheet1!$E$10:$X$629,AH$9,0) -> 180 | AJ53: =SUM(M53:T53) -> 1620 | AK53: =SUM(AA53:AH53) -> 2250 | AL53: =IFERROR(AJ53-AK53,0) -> -630
A54: 810018870348 | B54: 2550493 | C54: I AM MAGIC FOUNDATION 630 CAPRI | E54: 1000145 | F54: 021 | G54: 3453 - JUVIA'S PLACE | H54: F | I54: A | J54: BASC | K54: 14.4 | L54: 20 | M54: 90 | N54: 0 | O54: 180 | P54: 90 | Q54: 90 | R54: 180 | S54: 180 | T54: 0 | U54: 180 | V54: 90 | W54: 270 | X54: 0 | Z54: =VLOOKUP(E54,Sheet2!$A$1:$A$39,1,0) -> #N/A | AA54: =VLOOKUP($E54,[1]Sheet1!$E$10:$X$629,AA$9,0) -> 270 | AB54: =VLOOKUP($E54,[1]Sheet1!$E$10:$X$629,AB$9,0) -> 180 | AC54: =VLOOKUP($E54,[1]Sheet1!$E$10:$X$629,AC$9,0) -> 270 | AD54: =VLOOKUP($E54,[1]Sheet1!$E$10:$X$629,AD$9,0) -> 180 | AE54: =VLOOKUP($E54,[1]Sheet1!$E$10:$X$629,AE$9,0) -> 180 | AF54: =VLOOKUP($E54,[1]Sheet1!$E$10:$X$629,AF$9,0) -> 270 | AG54: =VLOOKUP($E54,[1]Sheet1!$E$10:$X$629,AG$9,0) -> 180 | AH54: =VLOOKUP($E54,[1]Sheet1!$E$10:$X$629,AH$9,0) -> 180 | AJ54: =SUM(M54:T54) -> 810 | AK54: =SUM(AA54:AH54) -> 1710 | AL54: =IFERROR(AJ54-AK54,0) -> -900
A55: 810018870362 | B55: 2550494 | C55: I AM MAGIC FOUNDATION 650 ALEXANDRIA | E55: 1000147 | F55: 021 | G55: 3453 - JUVIA'S PLACE | H55: F | I55: A | J55: BASC | K55: 14.4 | L55: 20 | M55: 0 | N55: 180 | O55: 180 | P55: 90 | Q55: 270 | R55: 180 | S55: 90 | T55: 270 | U55: 180 | V55: 180 | W55: 270 | X55: 180 | Z55: =VLOOKUP(E55,Sheet2!$A$1:$A$39,1,0) -> #N/A | AA55: =VLOOKUP($E55,[1]Sheet1!$E$10:$X$629,AA$9,0) -> 270 | AB55: =VLOOKUP($E55,[1]Sheet1!$E$10:$X$629,AB$9,0) -> 90 | AC55: =VLOOKUP($E55,[1]Sheet1!$E$10:$X$629,AC$9,0) -> 360 | AD55: =VLOOKUP($E55,[1]Sheet1!$E$10:$X$629,AD$9,0) -> 270 | AE55: =VLOOKUP($E55,[1]Sheet1!$E$10:$X$629,AE$9,0) -> 360 | AF55: =VLOOKUP($E55,[1]Sheet1!$E$10:$X$629,AF$9,0) -> 270 | AG55: =VLOOKUP($E55,[1]Sheet1!$E$10:$X$629,AG$9,0) -> 270 | AH55: =VLOOKUP($E55,[1]Sheet1!$E$10:$X$629,AH$9,0) -> 180 | AJ55: =SUM(M55:T55) -> 1260 | AK55: =SUM(AA55:AH55) -> 2070 | AL55: =IFERROR(AJ55-AK55,0) -> -810
A56: 810018870201 | B56: 2550495 | C56: I AM MAGIC FOUNDATION 420 HAVANNA | E56: 1000131 | F56: 021 | G56: 3453 - JUVIA'S PLACE | H56: F | I56: A | J56: BASC | K56: 14.4 | L56: 20 | M56: 90 | N56: 0 | O56: 270 | P56: 0 | Q56: 90 | R56: 180 | S56: 0 | T56: 90 | U56: 180 | V56: 90 | W56: 90 | X56: 90 | Z56: =VLOOKUP(E56,Sheet2!$A$1:$A$39,1,0) -> #N/A | AA56: =VLOOKUP($E56,[1]Sheet1!$E$10:$X$629,AA$9,0) -> 180 | AB56: =VLOOKUP($E56,[1]Sheet1!$E$10:$X$629,AB$9,0) -> 90 | AC56: =VLOOKUP($E56,[1]Sheet1!$E$10:$X$629,AC$9,0) -> 360 | AD56: =VLOOKUP($E56,[1]Sheet1!$E$10:$X$629,AD$9,0) -> 180 | AE56: =VLOOKUP($E56,[1]Sheet1!$E$10:$X$629,AE$9,0) -> 270 | AF56: =VLOOKUP($E56,[1]Sheet1!$E$10:$X$629,AF$9,0) -> 270 | AG56: =VLOOKUP($E56,[1]Sheet1!$E$10:$X$629,AG$9,0) -> 180 | AH56: =VLOOKUP($E56,[1]Sheet1!$E$10:$X$629,AH$9,0) -> 90 | AJ56: =SUM(M56:T56) -> 720 | AK56: =SUM(AA56:AH56) -> 1620 | AL56: =IFERROR(AJ56-AK56,0) -> -900
A57: 810018870317 | B57: 2550496 | C57: I AM MAGIC FOUNDATION 600 CAIRO | E57: 1000142 | F57: 021 | G57: 3453 - JUVIA'S PLACE | H57: F | I57: A | J57: BASC | K57: 14.4 | L57: 20 | M57: 270 | N57: 270 | O57: 180 | P57: 270 | Q57: 270 | R57: 270 | S57: 180 | T57: 270 | U57: 270 | V57: 360 | W57: 180 | X57: 360 | Z57: =VLOOKUP(E57,Sheet2!$A$1:$A$39,1,0) -> #N/A | AA57: =VLOOKUP($E57,[1]Sheet1!$E$10:$X$629,AA$9,0) -> 360 | AB57: =VLOOKUP($E57,[1]Sheet1!$E$10:$X$629,AB$9,0) -> 360 | AC57: =VLOOKUP($E57,[1]Sheet1!$E$10:$X$629,AC$9,0) -> 360 | AD57: =VLOOKUP($E57,[1]Sheet1!$E$10:$X$629,AD$9,0) -> 270 | AE57: =VLOOKUP($E57,[1]Sheet1!$E$10:$X$629,AE$9,0) -> 450 | AF57: =VLOOKUP($E57,[1]Sheet1!$E$10:$X$629,AF$9,0) -> 360 | AG57: =VLOOKUP($E57,[1]Sheet1!$E$10:$X$629,AG$9,0) -> 450 | AH57: =VLOOKUP($E57,[1]Sheet1!$E$10:$X$629,AH$9,0) -> 90 | AJ57: =SUM(M57:T57) -> 1980 | AK57: =SUM(AA57:AH57) -> 2700 | AL57: =IFERROR(AJ57-AK57,0) -> -720
A58: 810018870294 | B58: 2550497 | C58: I AM MAGIC FOUNDATION 540 GIZA | E58: 1000140 | F58: 021 | G58: 3453 - JUVIA'S PLACE | H58: F | I58: A | J58: BASC | K58: 14.4 | L58: 20 | M58: 90 | N58: 180 | O58: 180 | P58: 180 | Q58: 270 | R58: 90 | S58: 270 | T58: 90 | U58: 360 | V58: 180 | W58: 180 | X58: 270 | Z58: =VLOOKUP(E58,Sheet2!$A$1:$A$39,1,0) -> #N/A | AA58: =VLOOKUP($E58,[1]Sheet1!$E$10:$X$629,AA$9,0) -> 360 | AB58: =VLOOKUP($E58,[1]Sheet1!$E$10:$X$629,AB$9,0) -> 360 | AC58: =VLOOKUP($E58,[1]Sheet1!$E$10:$X$629,AC$9,0) -> 270 | AD58: =VLOOKUP($E58,[1]Sheet1!$E$10:$X$629,AD$9,0) -> 270 | AE58: =VLOOKUP($E58,[1]Sheet1!$E$10:$X$629,AE$9,0) -> 360 | AF58: =VLOOKUP($E58,[1]Sheet1!$E$10:$X$629,AF$9,0) -> 270 | AG58: =VLOOKUP($E58,[1]Sheet1!$E$10:$X$629,AG$9,0) -> 270 | AH58: =VLOOKUP($E58,[1]Sheet1!$E$10:$X$629,AH$9,0) -> 180 | AJ58: =SUM(M58:T58) -> 1350 | AK58: =SUM(AA58:AH58) -> 2340 | AL58: =IFERROR(AJ58-AK58,0) -> -990
A59: 810018870188 | B59: 2550498 | C59: I AM MAGIC FOUNDATION 400 ETHIOPIA | E59: 1000129 | F59: 021 | G59: 3453 - JUVIA'S PLACE | H59: F | I59: A | J59: BASC | K59: 14.4 | L59: 20 | M59: 0 | N59: 180 | O59: 0 | P59: 270 | Q59: 90 | R59: 90 | S59: 90 | T59: 270 | U59: 0 | V59: 270 | W59: 90 | X59: 180 | Z59: =VLOOKUP(E59,Sheet2!$A$1:$A$39,1,0) -> #N/A | AA59: =VLOOKUP($E59,[1]Sheet1!$E$10:$X$629,AA$9,0) -> 90 | AB59: =VLOOKUP($E59,[1]Sheet1!$E$10:$X$629,AB$9,0) -> 180 | AC59: =VLOOKUP($E59,[1]Sheet1!$E$10:$X$629,AC$9,0) -> 270 | AD59: =VLOOKUP($E59,[1]Sheet1!$E$10:$X$629,AD$9,0) -> 270 | AE59: =VLOOKUP($E59,[1]Sheet1!$E$10:$X$629,AE$9,0) -> 270 | AF59: =VLOOKUP($E59,[1]Sheet1!$E$10:$X$629,AF$9,0) -> 270 | AG59: =VLOOKUP($E59,[1]Sheet1!$E$10:$X$629,AG$9,0) -> 270 | AH59: =VLOOKUP($E59,[1]Sheet1!$E$10:$X$629,AH$9,0) -> 180 | AJ59: =SUM(M59:T59) -> 990 | AK59: =SUM(AA59:AH59) -> 1800 | AL59: =IFERROR(AJ59-AK59,0) -> -810
A60: 810018870157 | B60: 2550499 | C60: I AM MAGIC FOUNDATION 330 ACCRA | E60: 1000126 | F60: 021 | G60: 3453 - JUVIA'S PLACE | H60: F | I60: A | J60: BASC | K60: 14.4 | L60: 20 | M60: 180 | N60: 90 | O60: 90 | P60: 180 | Q60: 180 | R60: 0 | S60: 360 | T60: 0 | U60: 270 | V60: 180 | W60: 270 | X60: 0 | Z60: =VLOOKUP(E60,Sheet2!$A$1:$A$39,1,0) -> #N/A | AA60: =VLOOKUP($E60,[1]Sheet1!$E$10:$X$629,AA$9,0) -> 360 | AB60: =VLOOKUP($E60,[1]Sheet1!$E$10:$X$629,AB$9,0) -> 270 | AC60: =VLOOKUP($E60,[1]Sheet1!$E$10:$X$629,AC$9,0) -> 360 | AD60: =VLOOKUP($E60,[1]Sheet1!$E$10:$X$629,AD$9,0) -> 450 | AE60: =VLOOKUP($E60,[1]Sheet1!$E$10:$X$629,AE$9,0) -> 450 | AF60: =VLOOKUP($E60,[1]Sheet1!$E$10:$X$629,AF$9,0) -> 270 | AG60: =VLOOKUP($E60,[1]Sheet1!$E$10:$X$629,AG$9,0) -> 450 | AH60: =VLOOKUP($E60,[1]Sheet1!$E$10:$X$629,AH$9,0) -> 270 | AJ60: =SUM(M60:T60) -> 1080 | AK60: =SUM(AA60:AH60) -> 2880 | AL60: =IFERROR(AJ60-AK60,0) -> -1800
A61: 810018870232 | B61: 2550500 | C61: I AM MAGIC FOUNDATION 440 SAVANNA | E61: 1000134 | F61: 021 | G61: 3453 - JUVIA'S PLACE | H61: F | I61: A | J61: BASC | K61: 14.4 | L61: 20 | M61: 90 | N61: 90 | O61: 90 | P61: 360 | Q61: 0 | R61: 360 | S61: 90 | T61: 180 | U61: 270 | V61: 180 | W61: 270 | X61: 180 | Z61: =VLOOKUP(E61,Sheet2!$A$1:$A$39,1,0) -> #N/A | AA61: =VLOOKUP($E61,[1]Sheet1!$E$10:$X$629,AA$9,0) -> 360 | AB61: =VLOOKUP($E61,[1]Sheet1!$E$10:$X$629,AB$9,0) -> 450 | AC61: =VLOOKUP($E61,[1]Sheet1!$E$10:$X$629,AC$9,0) -> 360 | AD61: =VLOOKUP($E61,[1]Sheet1!$E$10:$X$629,AD$9,0) -> 540 | AE61: =VLOOKUP($E61,[1]Sheet1!$E$10:$X$629,AE$9,0) -> 450 | AF61: =VLOOKUP($E61,[1]Sheet1!$E$10:$X$629,AF$9,0) -> 360 | AG61: =VLOOKUP($E61,[1]Sheet1!$E$10:$X$629,AG$9,0) -> 540 | AH61: =VLOOKUP($E61,[1]Sheet1!$E$10:$X$629,AH$9,0) -> 90 | AJ61: =SUM(M61:T61) -> 1260 | AK61: =SUM(AA61:AH61) -> 3150 | AL61: =IFERROR(AJ61-AK61,0) -> -1890
A62: 810018870263 | B62: 2550501 | C62: I AM MAGIC FOUNDATION 510 ARUBA | E62: 1000137 | F62: 021 | G62: 3453 - JUVIA'S PLACE | H62: F | I62: A | J62: BASC | K62: 14.4 | L62: 20 | M62: 180 | N62: 0 | O62: 180 | P62: 90 | Q62: 270 | R62: 90 | S62: 180 | T62: 0 | U62: 360 | V62: 0 | W62: 270 | X62: 180 | Z62: =VLOOKUP(E62,Sheet2!$A$1:$A$39,1,0) -> #N/A | AA62: =VLOOKUP($E62,[1]Sheet1!$E$10:$X$629,AA$9,0) -> 360 | AB62: =VLOOKUP($E62,[1]Sheet1!$E$10:$X$629,AB$9,0) -> 180 | AC62: =VLOOKUP($E62,[1]Sheet1!$E$10:$X$629,AC$9,0) -> 360 | AD62: =VLOOKUP($E62,[1]Sheet1!$E$10:$X$629,AD$9,0) -> 180 | AE62: =VLOOKUP($E62,[1]Sheet1!$E$10:$X$629,AE$9,0) -> 270 | AF62: =VLOOKUP($E62,[1]Sheet1!$E$10:$X$629,AF$9,0) -> 450 | AG62: =VLOOKUP($E62,[1]Sheet1!$E$10:$X$629,AG$9,0) -> 270 | AH62: =VLOOKUP($E62,[1]Sheet1!$E$10:$X$629,AH$9,0) -> 90 | AJ62: =SUM(M62:T62) -> 990 | AK62: =SUM(AA62:AH62) -> 2160 | AL62: =IFERROR(AJ62-AK62,0) -> -1170
... A70: 810018870386 | B70: 2550509 | C70: I AM MAGIC FOUNDATION 710 MARICAO | E70: 1000149 | F70: 021 | G70: 3453 - JUVIA'S PLACE | H70: F | I70: A | J70: BASC | K70: 14.4 | L70: 20 | M70: 90 | N70: 180 | O70: 180 | P70: 180 | Q70: 180 | R70: 90 | S70: 270 | T70: 90 | U70: 270 | V70: 180 | W70: 270 | X70: 270 | Z70: =VLOOKUP(E70,Sheet2!$A$1:$A$39,1,0) -> #N/A | AA70: =VLOOKUP($E70,[1]Sheet1!$E$10:$X$629,AA$9,0) -> 180 | AB70: =VLOOKUP($E70,[1]Sheet1!$E$10:$X$629,AB$9,0) -> 270 | AC70: =VLOOKUP($E70,[1]Sheet1!$E$10:$X$629,AC$9,0) -> 360 | AD70: =VLOOKUP($E70,[1]Sheet1!$E$10:$X$629,AD$9,0) -> 180 | AE70: =VLOOKUP($E70,[1]Sheet1!$E$10:$X$629,AE$9,0) -> 450 | AF70: =VLOOKUP($E70,[1]Sheet1!$E$10:$X$629,AF$9,0) -> 270 | AG70: =VLOOKUP($E70,[1]Sheet1!$E$10:$X$629,AG$9,0) -> 270 | AH70: =VLOOKUP($E70,[1]Sheet1!$E$10:$X$629,AH$9,0) -> 180 | AJ70: =SUM(M70:T70) -> 1260 | AK70: =SUM(AA70:AH70) -> 2160 | AL70: =IFERROR(AJ70-AK70,0) -> -900
A71: 810018870416 | B71: 2550510 | C71: I AM MAGIC FOUNDATION 740 MARISOL | E71: 1000152 | F71: 021 | G71: 3453 - JUVIA'S PLACE | I71: A | J71: BASC | K71: 14.4 | L71: 20 | M71: 0 | N71: 0 | O71: 0 | P71: 0 | Q71: 0 | R71: 0 | S71: 0 | T71: 0 | U71: 0 | V71: 0 | W71: 0 | X71: 0 | Z71: =VLOOKUP(E71,Sheet2!$A$1:$A$39,1,0) -> #N/A | AA71: =VLOOKUP($E71,[1]Sheet1!$E$10:$X$629,AA$9,0) -> 0 | AB71: =VLOOKUP($E71,[1]Sheet1!$E$10:$X$629,AB$9,0) -> 0 | AC71: =VLOOKUP($E71,[1]Sheet1!$E$10:$X$629,AC$9,0) -> 0 | AD71: =VLOOKUP($E71,[1]Sheet1!$E$10:$X$629,AD$9,0) -> 0 | AE71: =VLOOKUP($E71,[1]Sheet1!$E$10:$X$629,AE$9,0) -> 0 | AF71: =VLOOKUP($E71,[1]Sheet1!$E$10:$X$629,AF$9,0) -> 0 | AG71: =VLOOKUP($E71,[1]Sheet1!$E$10:$X$629,AG$9,0) -> 0 | AH71: =VLOOKUP($E71,[1]Sheet1!$E$10:$X$629,AH$9,0) -> 0 | AJ71: =SUM(M71:T71) -> 0 | AK71: =SUM(AA71:AH71) -> 0 | AL71: =IFERROR(AJ71-AK71,0) -> 0
A72: 810018870126 | B72: 2550511 | C72: I AM MAGIC FOUNDATION 300 GABON | E72: 1000123 | F72: 021 | G72: 3453 - JUVIA'S PLACE | H72: F | I72: A | J72: BASC | K72: 14.4 | L72: 20 | M72: 270 | N72: 180 | O72: 270 | P72: 90 | Q72: 360 | R72: 180 | S72: 180 | T72: 270 | U72: 360 | V72: 360 | W72: 90 | X72: 360 | Z72: =VLOOKUP(E72,Sheet2!$A$1:$A$39,1,0) -> #N/A | AA72: =VLOOKUP($E72,[1]Sheet1!$E$10:$X$629,AA$9,0) -> 360 | AB72: =VLOOKUP($E72,[1]Sheet1!$E$10:$X$629,AB$9,0) -> 450 | AC72: =VLOOKUP($E72,[1]Sheet1!$E$10:$X$629,AC$9,0) -> 540 | AD72: =VLOOKUP($E72,[1]Sheet1!$E$10:$X$629,AD$9,0) -> 270 | AE72: =VLOOKUP($E72,[1]Sheet1!$E$10:$X$629,AE$9,0) -> 540 | AF72: =VLOOKUP($E72,[1]Sheet1!$E$10:$X$629,AF$9,0) -> 450 | AG72: =VLOOKUP($E72,[1]Sheet1!$E$10:$X$629,AG$9,0) -> 360 | AH72: =VLOOKUP($E72,[1]Sheet1!$E$10:$X$629,AH$9,0) -> 270 | AJ72: =SUM(M72:T72) -> 1800 | AK72: =SUM(AA72:AH72) -> 3240 | AL72: =IFERROR(AJ72-AK72,0) -> -1440
A73: 810018870393 | B73: 2550512 | C73: I AM MAGIC FOUNDATION 720 BALI | E73: 1000150 | F73: 021 | G73: 3453 - JUVIA'S PLACE | H73: F | I73: A | J73: BASC | K73: 14.4 | L73: 20 | M73: 90 | N73: 90 | O73: 180 | P73: 90 | Q73: 180 | R73: 270 | S73: 90 | T73: 180 | U73: 90 | V73: 360 | W73: 180 | X73: 180 | Z73: =VLOOKUP(E73,Sheet2!$A$1:$A$39,1,0) -> #N/A | AA73: =VLOOKUP($E73,[1]Sheet1!$E$10:$X$629,AA$9,0) -> 270 | AB73: =VLOOKUP($E73,[1]Sheet1!$E$10:$X$629,AB$9,0) -> 180 | AC73: =VLOOKUP($E73,[1]Sheet1!$E$10:$X$629,AC$9,0) -> 270 | AD73: =VLOOKUP($E73,[1]Sheet1!$E$10:$X$629,AD$9,0) -> 270 | AE73: =VLOOKUP($E73,[1]Sheet1!$E$10:$X$629,AE$9,0) -> 360 | AF73: =VLOOKUP($E73,[1]Sheet1!$E$10:$X$629,AF$9,0) -> 270 | AG73: =VLOOKUP($E73,[1]Sheet1!$E$10:$X$629,AG$9,0) -> 360 | AH73: =VLOOKUP($E73,[1]Sheet1!$E$10:$X$629,AH$9,0) -> 90 | AJ73: =SUM(M73:T73) -> 1170 | AK73: =SUM(AA73:AH73) -> 2070 | AL73: =IFERROR(AJ73-AK73,0) -> -900
A74: 810018870270 | B74: 2550513 | C74: I AM MAGIC FOUNDATION 520 TANGIER | E74: 1000138 | F74: 021 | G74: 3453 - JUVIA'S PLACE | H74: F | I74: A | J74: BASC | K74: 14.4 | L74: 20 | M74: 180 | N74: 180 | O74: 90 | P74: 180 | Q74: 90 | R74: 0 | S74: 360 | T74: 90 | U74: 180 | V74: 90 | W74: 270 | X74: 90 | Z74: =VLOOKUP(E74,Sheet2!$A$1:$A$39,1,0) -> #N/A | AA74: =VLOOKUP($E74,[1]Sheet1!$E$10:$X$629,AA$9,0) -> 360 | AB74: =VLOOKUP($E74,[1]Sheet1!$E$10:$X$629,AB$9,0) -> 270 | AC74: =VLOOKUP($E74,[1]Sheet1!$E$10:$X$629,AC$9,0) -> 270 | AD74: =VLOOKUP($E74,[1]Sheet1!$E$10:$X$629,AD$9,0) -> 450 | AE74: =VLOOKUP($E74,[1]Sheet1!$E$10:$X$629,AE$9,0) -> 270 | AF74: =VLOOKUP($E74,[1]Sheet1!$E$10:$X$629,AF$9,0) -> 360 | AG74: =VLOOKUP($E74,[1]Sheet1!$E$10:$X$629,AG$9,0) -> 450 | AH74: =VLOOKUP($E74,[1]Sheet1!$E$10:$X$629,AH$9,0) -> 90 | AJ74: =SUM(M74:T74) -> 1170 | AK74: =SUM(AA74:AH74) -> 2520 | AL74: =IFERROR(AJ74-AK74,0) -> -1350
A75: 810018870225 | B75: 2550514 | C75: I AM MAGIC FOUNDATION 435 PUNTA CANA | E75: 1000133 | F75: 021 | G75: 3453 - JUVIA'S PLACE | H75: F | I75: A | J75: BASC | K75: 14.4 | L75: 20 | M75: 90 | N75: 90 | O75: 180 | P75: 90 | Q75: 180 | R75: 90 | S75: 270 | T75: 90 | U75: 270 | V75: 90 | W75: 270 | X75: 90 | Z75: =VLOOKUP(E75,Sheet2!$A$1:$A$39,1,0) -> #N/A | AA75: =VLOOKUP($E75,[1]Sheet1!$E$10:$X$629,AA$9,0) -> 360 | AB75: =VLOOKUP($E75,[1]Sheet1!$E$10:$X$629,AB$9,0) -> 180 | AC75: =VLOOKUP($E75,[1]Sheet1!$E$10:$X$629,AC$9,0) -> 540 | AD75: =VLOOKUP($E75,[1]Sheet1!$E$10:$X$629,AD$9,0) -> 270 | AE75: =VLOOKUP($E75,[1]Sheet1!$E$10:$X$629,AE$9,0) -> 360 | AF75: =VLOOKUP($E75,[1]Sheet1!$E$10:$X$629,AF$9,0) -> 450 | AG75: =VLOOKUP($E75,[1]Sheet1!$E$10:$X$629,AG$9,0) -> 540 | AH75: =VLOOKUP($E75,[1]Sheet1!$E$10:$X$629,AH$9,0) -> 180 | AJ75: =SUM(M75:T75) -> 1080 | AK75: =SUM(AA75:AH75) -> 2880 | AL75: =IFERROR(AJ75-AK75,0) -> -1800
A76: 810018870331 | B76: 2550515 | C76: I AM MAGIC FOUNDATION 620 FES | E76: 1000144 | F76: 021 | G76: 3453 - JUVIA'S PLACE | H76: F | I76: A | J76: BASC | K76: 14.4 | L76: 20 | M76: 90 | N76: 90 | O76: 180 | P76: 0 | Q76: 180 | R76: 90 | S76: 0 | T76: 270 | U76: 90 | V76: 180 | W76: 90 | X76: 90 | Z76: =VLOOKUP(E76,Sheet2!$A$1:$A$39,1,0) -> #N/A | AA76: =VLOOKUP($E76,[1]Sheet1!$E$10:$X$629,AA$9,0) -> 360 | AB76: =VLOOKUP($E76,[1]Sheet1!$E$10:$X$629,AB$9,0) -> 90 | AC76: =VLOOKUP($E76,[1]Sheet1!$E$10:$X$629,AC$9,0) -> 270 | AD76: =VLOOKUP($E76,[1]Sheet1!$E$10:$X$629,AD$9,0) -> 360 | AE76: =VLOOKUP($E76,[1]Sheet1!$E$10:$X$629,AE$9,0) -> 90 | AF76: =VLOOKUP($E76,[1]Sheet1!$E$10:$X$629,AF$9,0) -> 360 | AG76: =VLOOKUP($E76,[1]Sheet1!$E$10:$X$629,AG$9,0) -> 180 | AH76: =VLOOKUP($E76,[1]Sheet1!$E$10:$X$629,AH$9,0) -> 180 | AJ76: =SUM(M76:T76) -> 900 | AK76: =SUM(AA76:AH76) -> 1890 | AL76: =IFERROR(AJ76-AK76,0) -> -990
A77: 810018870379 | B77: 2550516 | C77: I AM MAGIC FOUNDATION 700 VIENNA | E77: 1000148 | F77: 021 | G77: 3453 - JUVIA'S PLACE | H77: F | I77: A | J77: BASC | K77: 14.4 | L77: 20 | M77: 270 | N77: 0 | O77: 270 | P77: 0 | Q77: 0 | R77: 360 | S77: 90 | T77: 90 | U77: 180 | V77: 90 | W77: 270 | X77: 90 | Z77: =VLOOKUP(E77,Sheet2!$A$1:$A$39,1,0) -> #N/A | AA77: =VLOOKUP($E77,[1]Sheet1!$E$10:$X$629,AA$9,0) -> 90 | AB77: =VLOOKUP($E77,[1]Sheet1!$E$10:$X$629,AB$9,0) -> 270 | AC77: =VLOOKUP($E77,[1]Sheet1!$E$10:$X$629,AC$9,0) -> 360 | AD77: =VLOOKUP($E77,[1]Sheet1!$E$10:$X$629,AD$9,0) -> 0 | AE77: =VLOOKUP($E77,[1]Sheet1!$E$10:$X$629,AE$9,0) -> 270 | AF77: =VLOOKUP($E77,[1]Sheet1!$E$10:$X$629,AF$9,0) -> 450 | AG77: =VLOOKUP($E77,[1]Sheet1!$E$10:$X$629,AG$9,0) -> 180 | AH77: =VLOOKUP($E77,[1]Sheet1!$E$10:$X$629,AH$9,0) -> 90 | AJ77: =SUM(M77:T77) -> 1080 | AK77: =SUM(AA77:AH77) -> 1710 | AL77: =IFERROR(AJ77-AK77,0) -> -630
A78: 810018870249 | B78: 2550517 | C78: I AM MAGIC FOUNDATION 450 CASABLANCA | E78: 1000135 | F78: 021 | G78: 3453 - JUVIA'S PLACE | I78: A | J78: BASC | K78: 14.4 | L78: 20 | M78: 0 | N78: 0 | O78: 0 | P78: 0 | Q78: 0 | R78: 0 | S78: 0 | T78: 0 | U78: 0 | V78: 0 | W78: 0 | X78: 0 | Z78: =VLOOKUP(E78,Sheet2!$A$1:$A$39,1,0) -> #N/A | AA78: =VLOOKUP($E78,[1]Sheet1!$E$10:$X$629,AA$9,0) -> 0 | AB78: =VLOOKUP($E78,[1]Sheet1!$E$10:$X$629,AB$9,0) -> 0 | AC78: =VLOOKUP($E78,[1]Sheet1!$E$10:$X$629,AC$9,0) -> 0 | AD78: =VLOOKUP($E78,[1]Sheet1!$E$10:$X$629,AD$9,0) -> 0 | AE78: =VLOOKUP($E78,[1]Sheet1!$E$10:$X$629,AE$9,0) -> 0 | AF78: =VLOOKUP($E78,[1]Sheet1!$E$10:$X$629,AF$9,0) -> 0 | AG78: =VLOOKUP($E78,[1]Sheet1!$E$10:$X$629,AG$9,0) -> 0 | AH78: =VLOOKUP($E78,[1]Sheet1!$E$10:$X$629,AH$9,0) -> 0 | AJ78: =SUM(M78:T78) -> 0 | AK78: =SUM(AA78:AH78) -> 0 | AL78: =IFERROR(AJ78-AK78,0) -> 0
A79: 810018870256 | B79: 2550518 | C79: I AM MAGIC FOUNDATION 500 BOGOTA | E79: 1000136 | F79: 021 | G79: 3453 - JUVIA'S PLACE | I79: A | J79: BASC | K79: 14.4 | L79: 20 | M79: 0 | N79: 0 | O79: 0 | P79: 0 | Q79: 0 | R79: 0 | S79: 0 | T79: 0 | U79: 0 | V79: 0 | W79: 0 | X79: 0 | Z79: =VLOOKUP(E79,Sheet2!$A$1:$A$39,1,0) -> #N/A | AA79: =VLOOKUP($E79,[1]Sheet1!$E$10:$X$629,AA$9,0) -> 0 | AB79: =VLOOKUP($E79,[1]Sheet1!$E$10:$X$629,AB$9,0) -> 0 | AC79: =VLOOKUP($E79,[1]Sheet1!$E$10:$X$629,AC$9,0) -> 0 | AD79: =VLOOKUP($E79,[1]Sheet1!$E$10:$X$629,AD$9,0) -> 0 | AE79: =VLOOKUP($E79,[1]Sheet1!$E$10:$X$629,AE$9,0) -> 0 | AF79: =VLOOKUP($E79,[1]Sheet1!$E$10:$X$629,AF$9,0) -> 0 | AG79: =VLOOKUP($E79,[1]Sheet1!$E$10:$X$629,AG$9,0) -> 0 | AH79: =VLOOKUP($E79,[1]Sheet1!$E$10:$X$629,AH$9,0) -> 0 | AJ79: =SUM(M79:T79) -> 0 | AK79: =SUM(AA79:AH79) -> 0 | AL79: =IFERROR(AJ79-AK79,0) -> 0
A80: 810018879914 | B80: 2551092 | C80: I AM MAGIC CONCEALER 7 | E80: 1000082 | F80: 021 | G80: 3453 - JUVIA'S PLACE | H80: F | I80: A | J80: BASC | K80: 9 | L80: 18 | M80: 144 | N80: 576 | O80: 432 | P80: 288 | Q80: 432 | R80: 576 | S80: 288 | T80: 432 | U80: 288 | V80: 432 | W80: 576 | X80: 432 | Z80: =VLOOKUP(E80,Sheet2!$A$1:$A$39,1,0) -> #N/A | AA80: =VLOOKUP($E80,[1]Sheet1!$E$10:$X$629,AA$9,0) -> 288 | AB80: =VLOOKUP($E80,[1]Sheet1!$E$10:$X$629,AB$9,0) -> 432 | AC80: =VLOOKUP($E80,[1]Sheet1!$E$10:$X$629,AC$9,0) -> 576 | AD80: =VLOOKUP($E80,[1]Sheet1!$E$10:$X$629,AD$9,0) -> 432 | AE80: =VLOOKUP($E80,[1]Sheet1!$E$10:$X$629,AE$9,0) -> 432 | AF80: =VLOOKUP($E80,[1]Sheet1!$E$10:$X$629,AF$9,0) -> 576 | AG80: =VLOOKUP($E80,[1]Sheet1!$E$10:$X$629,AG$9,0) -> 432 | AH80: =VLOOKUP($E80,[1]Sheet1!$E$10:$X$629,AH$9,0) -> 144 | AJ80: =SUM(M80:T80) -> 3168 | AK80: =SUM(AA80:AH80) -> 3312 | AL80: =IFERROR(AJ80-AK80,0) -> -144
A81: 810018879891 | B81: 2551093 | C81: I AM MAGIC CONCEALER 9 | E81: 1000084 | F81: 021 | G81: 3453 - JUVIA'S PLACE | H81: E | I81: A | J81: BASC | K81: 9 | L81: 18 | M81: 1152 | N81: 1584 | O81: 1584 | P81: 1152 | Q81: 1296 | R81: 1440 | S81: 1440 | T81: 1152 | U81: 1440 | V81: 1728 | W81: 1440 | X81: 1584 | Z81: =VLOOKUP(E81,Sheet2!$A$1:$A$39,1,0) -> #N/A | AA81: =VLOOKUP($E81,[1]Sheet1!$E$10:$X$629,AA$9,0) -> 1296 | AB81: =VLOOKUP($E81,[1]Sheet1!$E$10:$X$629,AB$9,0) -> 1440 | AC81: =VLOOKUP($E81,[1]Sheet1!$E$10:$X$629,AC$9,0) -> 1728 | AD81: =VLOOKUP($E81,[1]Sheet1!$E$10:$X$629,AD$9,0) -> 1152 | AE81: =VLOOKUP($E81,[1]Sheet1!$E$10:$X$629,AE$9,0) -> 1008 | AF81: =VLOOKUP($E81,[1]Sheet1!$E$10:$X$629,AF$9,0) -> 1872 | AG81: =VLOOKUP($E81,[1]Sheet1!$E$10:$X$629,AG$9,0) -> 1296 | AH81: =VLOOKUP($E81,[1]Sheet1!$E$10:$X$629,AH$9,0) -> 576 | AJ81: =SUM(M81:T81) -> 10800 | AK81: =SUM(AA81:AH81) -> 10368 | AL81: =IFERROR(AJ81-AK81,0) -> 432
A82: 810018879761 | B82: 2551094 | C82: I AM MAGIC CONCEALER 22 | E82: 1000593 | F82: 021 | G82: 3453 - JUVIA'S PLACE | H82: E | I82: A | J82: BASC | K82: 9 | L82: 18 | M82: 720 | N82: 432 | O82: 576 | P82: 432 | Q82: 576 | R82: 432 | S82: 576 | T82: 432 | U82: 864 | V82: 576 | W82: 864 | X82: 576 | Z82: =VLOOKUP(E82,Sheet2!$A$1:$A$39,1,0) -> #N/A | AA82: =VLOOKUP($E82,[1]Sheet1!$E$10:$X$629,AA$9,0) -> 576 | AB82: =VLOOKUP($E82,[1]Sheet1!$E$10:$X$629,AB$9,0) -> 432 | AC82: =VLOOKUP($E82,[1]Sheet1!$E$10:$X$629,AC$9,0) -> 864 | AD82: =VLOOKUP($E82,[1]Sheet1!$E$10:$X$629,AD$9,0) -> 432 | AE82: =VLOOKUP($E82,[1]Sheet1!$E$10:$X$629,AE$9,0) -> 576 | AF82: =VLOOKUP($E82,[1]Sheet1!$E$10:$X$629,AF$9,0) -> 432 | AG82: =VLOOKUP($E82,[1]Sheet1!$E$10:$X$629,AG$9,0) -> 576 | AH82: =VLOOKUP($E82,[1]Sheet1!$E$10:$X$629,AH$9,0) -> 288 | AJ82: =SUM(M82:T82) -> 4176 | AK82: =SUM(AA82:AH82) -> 4176 | AL82: =IFERROR(AJ82-AK82,0) -> 0
A83: 810018879907 | B83: 2551095 | C83: I AM MAGIC CONCEALER 8 | E83: 1000083 | F83: 021 | G83: 3453 - JUVIA'S PLACE | H83: F | I83: A | J83: BASC | K83: 9 | L83: 18 | M83: 1008 | N83: 576 | O83: 1008 | P83: 576 | Q83: 720 | R83: 864 | S83: 576 | T83: 864 | U83: 864 | V83: 576 | W83: 1008 | X83: 720 | Z83: =VLOOKUP(E83,Sheet2!$A$1:$A$39,1,0) -> #N/A | AA83: =VLOOKUP($E83,[1]Sheet1!$E$10:$X$629,AA$9,0) -> 1008 | AB83: =VLOOKUP($E83,[1]Sheet1!$E$10:$X$629,AB$9,0) -> 576 | AC83: =VLOOKUP($E83,[1]Sheet1!$E$10:$X$629,AC$9,0) -> 1008 | AD83: =VLOOKUP($E83,[1]Sheet1!$E$10:$X$629,AD$9,0) -> 864 | AE83: =VLOOKUP($E83,[1]Sheet1!$E$10:$X$629,AE$9,0) -> 576 | AF83: =VLOOKUP($E83,[1]Sheet1!$E$10:$X$629,AF$9,0) -> 1008 | AG83: =VLOOKUP($E83,[1]Sheet1!$E$10:$X$629,AG$9,0) -> 720 | AH83: =VLOOKUP($E83,[1]Sheet1!$E$10:$X$629,AH$9,0) -> 432 | AJ83: =SUM(M83:T83) -> 6192 | AK83: =SUM(AA83:AH83) -> 6192 | AL83: =IFERROR(AJ83-AK83,0) -> 0
A84: 810018879808 | B84: 2551096 | C84: I AM MAGIC CONCEALER 18 | E84: 1000588 | F84: 021 | G84: 3453 - JUVIA'S PLACE | H84: D | I84: A | J84: BASC | K84: 9 | L84: 18 | M84: 1872 | N84: 2448 | O84: 2592 | P84: 1872 | Q84: 1584 | R84: 2304 | S84: 1584 | T84: 1584 | U84: 2736 | V84: 3024 | W84: 1872 | X84: 3024 | Z84: =VLOOKUP(E84,Sheet2!$A$1:$A$39,1,0) -> #N/A | AA84: =VLOOKUP($E84,[1]Sheet1!$E$10:$X$629,AA$9,0) -> 2160 | AB84: =VLOOKUP($E84,[1]Sheet1!$E$10:$X$629,AB$9,0) -> 2016 | AC84: =VLOOKUP($E84,[1]Sheet1!$E$10:$X$629,AC$9,0) -> 2736 | AD84: =VLOOKUP($E84,[1]Sheet1!$E$10:$X$629,AD$9,0) -> 1584 | AE84: =VLOOKUP($E84,[1]Sheet1!$E$10:$X$629,AE$9,0) -> 1728 | AF84: =VLOOKUP($E84,[1]Sheet1!$E$10:$X$629,AF$9,0) -> 2448 | AG84: =VLOOKUP($E84,[1]Sheet1!$E$10:$X$629,AG$9,0) -> 1872 | AH84: =VLOOKUP($E84,[1]Sheet1!$E$10:$X$629,AH$9,0) -> 864 | AJ84: =SUM(M84:T84) -> 15840 | AK84: =SUM(AA84:AH84) -> 15408 | AL84: =IFERROR(AJ84-AK84,0) -> 432
A85: 810018879822 | B85: 2551097 | C85: I AM MAGIC CONCEALER 16 | E85: 1000586 | F85: 021 | G85: 3453 - JUVIA'S PLACE | H85: E | I85: A | J85: BASC | K85: 9 | L85: 18 | M85: 576 | N85: 864 | O85: 864 | P85: 864 | Q85: 864 | R85: 1008 | S85: 864 | T85: 720 | U85: 1008 | V85: 1152 | W85: 1008 | X85: 1152 | Z85: =VLOOKUP(E85,Sheet2!$A$1:$A$39,1,0) -> #N/A | AA85: =VLOOKUP($E85,[1]Sheet1!$E$10:$X$629,AA$9,0) -> 720 | AB85: =VLOOKUP($E85,[1]Sheet1!$E$10:$X$629,AB$9,0) -> 720 | AC85: =VLOOKUP($E85,[1]Sheet1!$E$10:$X$629,AC$9,0) -> 1296 | AD85: =VLOOKUP($E85,[1]Sheet1!$E$10:$X$629,AD$9,0) -> 1008 | AE85: =VLOOKUP($E85,[1]Sheet1!$E$10:$X$629,AE$9,0) -> 720 | AF85: =VLOOKUP($E85,[1]Sheet1!$E$10:$X$629,AF$9,0) -> 1152 | AG85: =VLOOKUP($E85,[1]Sheet1!$E$10:$X$629,AG$9,0) -> 864 | AH85: =VLOOKUP($E85,[1]Sheet1!$E$10:$X$629,AH$9,0) -> 432 | AJ85: =SUM(M85:T85) -> 6624 | AK85: =SUM(AA85:AH85) -> 6912 | AL85: =IFERROR(AJ85-AK85,0) -> -288
A86: 810018879921 | B86: 2551098 | C86: I AM MAGIC CONCEALER 6 | E86: 1000081 | F86: 021 | G86: 3453 - JUVIA'S PLACE | H86: F | I86: A | J86: BASC | K86: 9 | L86: 18 | M86: 288 | N86: 144 | O86: 0 | P86: 288 | Q86: 0 | R86: 432 | S86: 0 | T86: 144 | U86: 144 | V86: 144 | W86: 288 | X86: 144 | Z86: =VLOOKUP(E86,Sheet2!$A$1:$A$39,1,0) -> #N/A | AA86: =VLOOKUP($E86,[1]Sheet1!$E$10:$X$629,AA$9,0) -> 144 | AB86: =VLOOKUP($E86,[1]Sheet1!$E$10:$X$629,AB$9,0) -> 432 | AC86: =VLOOKUP($E86,[1]Sheet1!$E$10:$X$629,AC$9,0) -> 144 | AD86: =VLOOKUP($E86,[1]Sheet1!$E$10:$X$629,AD$9,0) -> 432 | AE86: =VLOOKUP($E86,[1]Sheet1!$E$10:$X$629,AE$9,0) -> 0 | AF86: =VLOOKUP($E86,[1]Sheet1!$E$10:$X$629,AF$9,0) -> 576 | AG86: =VLOOKUP($E86,[1]Sheet1!$E$10:$X$629,AG$9,0) -> 144 | AH86: =VLOOKUP($E86,[1]Sheet1!$E$10:$X$629,AH$9,0) -> 0 | AJ86: =SUM(M86:T86) -> 1296 | AK86: =SUM(AA86:AH86) -> 1872 | AL86: =IFERROR(AJ86-AK86,0) -> -576
A87: 810018879976 | B87: 2551099 | C87: I AM MAGIC CONCEALER 1 | E87: 1000579 | F87: 021 | G87: 3453 - JUVIA'S PLACE | H87: F | I87: A | J87: BASC | K87: 9 | L87: 18 | M87: 0 | N87: 0 | O87: 144 | P87: 0 | Q87: 0 | R87: 144 | S87: 288 | T87: 0 | U87: 144 | V87: 0 | W87: 144 | X87: 0 | Z87: =VLOOKUP(E87,Sheet2!$A$1:$A$39,1,0) -> #N/A | AA87: =VLOOKUP($E87,[1]Sheet1!$E$10:$X$629,AA$9,0) -> 144 | AB87: =VLOOKUP($E87,[1]Sheet1!$E$10:$X$629,AB$9,0) -> 288 | AC87: =VLOOKUP($E87,[1]Sheet1!$E$10:$X$629,AC$9,0) -> 0 | AD87: =VLOOKUP($E87,[1]Sheet1!$E$10:$X$629,AD$9,0) -> 288 | AE87: =VLOOKUP($E87,[1]Sheet1!$E$10:$X$629,AE$9,0) -> 0 | AF87: =VLOOKUP($E87,[1]Sheet1!$E$10:$X$629,AF$9,0) -> 144 | AG87: =VLOOKUP($E87,[1]Sheet1!$E$10:$X$629,AG$9,0) -> 144 | AH87: =VLOOKUP($E87,[1]Sheet1!$E$10:$X$629,AH$9,0) -> 0 | AJ87: =SUM(M87:T87) -> 576 | AK87: =SUM(AA87:AH87) -> 1008 | AL87: =IFERROR(AJ87-AK87,0) -> -432
A88: 810018879815 | B88: 2551100 | C88: I AM MAGIC CONCEALER 17 | E88: 1000587 | F88: 021 | G88: 3453 - JUVIA'S PLACE | H88: F | I88: A | J88: BASC | K88: 9 | L88: 18 | M88: 432 | N88: 576 | O88: 576 | P88: 720 | Q88: 432 | R88: 720 | S88: 432 | T88: 432 | U88: 864 | V88: 576 | W88: 576 | X88: 720 | Z88: =VLOOKUP(E88,Sheet2!$A$1:$A$39,1,0) -> #N/A | AA88: =VLOOKUP($E88,[1]Sheet1!$E$10:$X$629,AA$9,0) -> 576 | AB88: =VLOOKUP($E88,[1]Sheet1!$E$10:$X$629,AB$9,0) -> 576 | AC88: =VLOOKUP($E88,[1]Sheet1!$E$10:$X$629,AC$9,0) -> 864 | AD88: =VLOOKUP($E88,[1]Sheet1!$E$10:$X$629,AD$9,0) -> 720 | AE88: =VLOOKUP($E88,[1]Sheet1!$E$10:$X$629,AE$9,0) -> 720 | AF88: =VLOOKUP($E88,[1]Sheet1!$E$10:$X$629,AF$9,0) -> 864 | AG88: =VLOOKUP($E88,[1]Sheet1!$E$10:$X$629,AG$9,0) -> 864 | AH88: =VLOOKUP($E88,[1]Sheet1!$E$10:$X$629,AH$9,0) -> 288 | AJ88: =SUM(M88:T88) -> 4320 | AK88: =SUM(AA88:AH88) -> 5472 | AL88: =IFERROR(AJ88-AK88,0) -> -1152
A89: 810018879792 | B89: 2551101 | C89: I AM MAGIC CONCEALER 19 | E89: 1000589 | F89: 021 | G89: 3453 - JUVIA'S PLACE | H89: D | I89: A | J89: BASC | K89: 9 | L89: 18 | M89: 2016 | N89: 2016 | O89: 2448 | P89: 1584 | Q89: 1872 | R89: 1872 | S89: 1152 | T89: 1584 | U89: 2736 | V89: 2880 | W89: 1728 | X89: 2736 | Z89: =VLOOKUP(E89,Sheet2!$A$1:$A$39,1,0) -> #N/A | AA89: =VLOOKUP($E89,[1]Sheet1!$E$10:$X$629,AA$9,0) -> 2592 | AB89: =VLOOKUP($E89,[1]Sheet1!$E$10:$X$629,AB$9,0) -> 1872 | AC89: =VLOOKUP($E89,[1]Sheet1!$E$10:$X$629,AC$9,0) -> 2592 | AD89: =VLOOKUP($E89,[1]Sheet1!$E$10:$X$629,AD$9,0) -> 1872 | AE89: =VLOOKUP($E89,[1]Sheet1!$E$10:$X$629,AE$9,0) -> 1440 | AF89: =VLOOKUP($E89,[1]Sheet1!$E$10:$X$629,AF$9,0) -> 2016 | AG89: =VLOOKUP($E89,[1]Sheet1!$E$10:$X$629,AG$9,0) -> 1584 | AH89: =VLOOKUP($E89,[1]Sheet1!$E$10:$X$629,AH$9,0) -> 864 | AJ89: =SUM(M89:T89) -> 14544 | AK89: =SUM(AA89:AH89) -> 14832 | AL89: =IFERROR(AJ89-AK89,0) -> -288
A90: 810018879952 | B90: 2551102 | C90: I AM MAGIC CONCEALER 3 | E90: 1000078 | F90: 021 | G90: 3453 - JUVIA'S PLACE | H90: F | I90: A | J90: BASC | K90: 9 | L90: 18 | M90: 0 | N90: 0 | O90: 144 | P90: 0 | Q90: 144 | R90: 0 | S90: 0 | T90: 144 | U90: 0 | V90: 0 | W90: 144 | X90: 144 | Z90: =VLOOKUP(E90,Sheet2!$A$1:$A$39,1,0) -> #N/A | AA90: =VLOOKUP($E90,[1]Sheet1!$E$10:$X$629,AA$9,0) -> 288 | AB90: =VLOOKUP($E90,[1]Sheet1!$E$10:$X$629,AB$9,0) -> 0 | AC90: =VLOOKUP($E90,[1]Sheet1!$E$10:$X$629,AC$9,0) -> 0 | AD90: =VLOOKUP($E90,[1]Sheet1!$E$10:$X$629,AD$9,0) -> 144 | AE90: =VLOOKUP($E90,[1]Sheet1!$E$10:$X$629,AE$9,0) -> 144 | AF90: =VLOOKUP($E90,[1]Sheet1!$E$10:$X$629,AF$9,0) -> 0 | AG90: =VLOOKUP($E90,[1]Sheet1!$E$10:$X$629,AG$9,0) -> 144 | AH90: =VLOOKUP($E90,[1]Sheet1!$E$10:$X$629,AH$9,0) -> 144 | AJ90: =SUM(M90:T90) -> 432 | AK90: =SUM(AA90:AH90) -> 864 | AL90: =IFERROR(AJ90-AK90,0) -> -432
A91: 810018879778 | B91: 2551103 | C91: I AM MAGIC CONCEALER 21 | E91: 1000592 | F91: 021 | G91: 3453 - JUVIA'S PLACE | H91: E | I91: A | J91: BASC | K91: 9 | L91: 18 | M91: 576 | N91: 432 | O91: 576 | P91: 432 | Q91: 576 | R91: 576 | S91: 432 | T91: 576 | U91: 432 | V91: 864 | W91: 576 | X91: 864 | Z91: =VLOOKUP(E91,Sheet2!$A$1:$A$39,1,0) -> #N/A | AA91: =VLOOKUP($E91,[1]Sheet1!$E$10:$X$629,AA$9,0) -> 576 | AB91: =VLOOKUP($E91,[1]Sheet1!$E$10:$X$629,AB$9,0) -> 576 | AC91: =VLOOKUP($E91,[1]Sheet1!$E$10:$X$629,AC$9,0) -> 720 | AD91: =VLOOKUP($E91,[1]Sheet1!$E$10:$X$629,AD$9,0) -> 432 | AE91: =VLOOKUP($E91,[1]Sheet1!$E$10:$X$629,AE$9,0) -> 432 | AF91: =VLOOKUP($E91,[1]Sheet1!$E$10:$X$629,AF$9,0) -> 720 | AG91: =VLOOKUP($E91,[1]Sheet1!$E$10:$X$629,AG$9,0) -> 576 | AH91: =VLOOKUP($E91,[1]Sheet1!$E$10:$X$629,AH$9,0) -> 288 | AJ91: =SUM(M91:T91) -> 4176 | AK91: =SUM(AA91:AH91) -> 4320 | AL91: =IFERROR(AJ91-AK91,0) -> -144
... A106: 810018879709 | B106: 2552142 | C106: I AM MAGIC LOOSE SETTING POWDER KALAHARI | E106: 1000823 | F106: 021 | G106: 3453 - JUVIA'S PLACE | H106: E | I106: DI | J106: BASC | K106: 7 | L106: 14 | M106: 0 | N106: 0 | O106: 0 | P106: 0 | Q106: 0 | R106: 0 | S106: 0 | T106: 0 | U106: 0 | V106: 0 | W106: 0 | X106: 0 | Z106: =VLOOKUP(E106,Sheet2!$A$1:$A$39,1,0) -> #N/A | AA106: =VLOOKUP($E106,[1]Sheet1!$E$10:$X$629,AA$9,0) -> 0 | AB106: =VLOOKUP($E106,[1]Sheet1!$E$10:$X$629,AB$9,0) -> 0 | AC106: =VLOOKUP($E106,[1]Sheet1!$E$10:$X$629,AC$9,0) -> 0 | AD106: =VLOOKUP($E106,[1]Sheet1!$E$10:$X$629,AD$9,0) -> 0 | AE106: =VLOOKUP($E106,[1]Sheet1!$E$10:$X$629,AE$9,0) -> 0 | AF106: =VLOOKUP($E106,[1]Sheet1!$E$10:$X$629,AF$9,0) -> 0 | AG106: =VLOOKUP($E106,[1]Sheet1!$E$10:$X$629,AG$9,0) -> 0 | AH106: =VLOOKUP($E106,[1]Sheet1!$E$10:$X$629,AH$9,0) -> 0 | AJ106: =SUM(M106:T106) -> 0 | AK106: =SUM(AA106:AH106) -> 0 | AL106: =IFERROR(AJ106-AK106,0) -> 0
A107: 810018879631 | B107: 2556432 | C107: SHADE STICK FOUNDATION | E107: 1000158 | F107: 021 | G107: 3453 - JUVIA'S PLACE | I107: X | J107: BASC | K107: 8 | L107: 3.99 | M107: 0 | N107: 0 | O107: 0 | P107: 0 | Q107: 0 | R107: 0 | S107: 0 | T107: 0 | U107: 0 | V107: 0 | W107: 0 | X107: 0 | Z107: =VLOOKUP(E107,Sheet2!$A$1:$A$39,1,0) -> #N/A | AA107: =VLOOKUP($E107,[1]Sheet1!$E$10:$X$629,AA$9,0) -> 0 | AB107: =VLOOKUP($E107,[1]Sheet1!$E$10:$X$629,AB$9,0) -> 0 | AC107: =VLOOKUP($E107,[1]Sheet1!$E$10:$X$629,AC$9,0) -> 0 | AD107: =VLOOKUP($E107,[1]Sheet1!$E$10:$X$629,AD$9,0) -> 0 | AE107: =VLOOKUP($E107,[1]Sheet1!$E$10:$X$629,AE$9,0) -> 0 | AF107: =VLOOKUP($E107,[1]Sheet1!$E$10:$X$629,AF$9,0) -> 0 | AG107: =VLOOKUP($E107,[1]Sheet1!$E$10:$X$629,AG$9,0) -> 0 | AH107: =VLOOKUP($E107,[1]Sheet1!$E$10:$X$629,AH$9,0) -> 0 | AJ107: =SUM(M107:T107) -> 0 | AK107: =SUM(AA107:AH107) -> 0 | AL107: =IFERROR(AJ107-AK107,0) -> 0
A108: 810018879600 | B108: 2556433 | C108: SHADE STICK FOUNDATION | E108: 1000154 | F108: 021 | G108: 3453 - JUVIA'S PLACE | I108: X | J108: BASC | K108: 8 | L108: 3.99 | M108: 0 | N108: 0 | O108: 0 | P108: 0 | Q108: 0 | R108: 0 | S108: 0 | T108: 0 | U108: 0 | V108: 0 | W108: 0 | X108: 0 | Z108: =VLOOKUP(E108,Sheet2!$A$1:$A$39,1,0) -> #N/A | AA108: =VLOOKUP($E108,[1]Sheet1!$E$10:$X$629,AA$9,0) -> 0 | AB108: =VLOOKUP($E108,[1]Sheet1!$E$10:$X$629,AB$9,0) -> 0 | AC108: =VLOOKUP($E108,[1]Sheet1!$E$10:$X$629,AC$9,0) -> 0 | AD108: =VLOOKUP($E108,[1]Sheet1!$E$10:$X$629,AD$9,0) -> 0 | AE108: =VLOOKUP($E108,[1]Sheet1!$E$10:$X$629,AE$9,0) -> 0 | AF108: =VLOOKUP($E108,[1]Sheet1!$E$10:$X$629,AF$9,0) -> 0 | AG108: =VLOOKUP($E108,[1]Sheet1!$E$10:$X$629,AG$9,0) -> 0 | AH108: =VLOOKUP($E108,[1]Sheet1!$E$10:$X$629,AH$9,0) -> 0 | AJ108: =SUM(M108:T108) -> 0 | AK108: =SUM(AA108:AH108) -> 0 | AL108: =IFERROR(AJ108-AK108,0) -> 0
A109: 810018879686 | B109: 2556434 | C109: SHADE STICK FOUNDATION | E109: 1000162 | F109: 021 | G109: 3453 - JUVIA'S PLACE | I109: X | J109: BASC | K109: 8 | L109: 3.99 | M109: 0 | N109: 0 | O109: 0 | P109: 0 | Q109: 0 | R109: 0 | S109: 0 | T109: 0 | U109: 0 | V109: 0 | W109: 0 | X109: 0 | Z109: =VLOOKUP(E109,Sheet2!$A$1:$A$39,1,0) -> #N/A | AA109: =VLOOKUP($E109,[1]Sheet1!$E$10:$X$629,AA$9,0) -> 0 | AB109: =VLOOKUP($E109,[1]Sheet1!$E$10:$X$629,AB$9,0) -> 0 | AC109: =VLOOKUP($E109,[1]Sheet1!$E$10:$X$629,AC$9,0) -> 0 | AD109: =VLOOKUP($E109,[1]Sheet1!$E$10:$X$629,AD$9,0) -> 0 | AE109: =VLOOKUP($E109,[1]Sheet1!$E$10:$X$629,AE$9,0) -> 0 | AF109: =VLOOKUP($E109,[1]Sheet1!$E$10:$X$629,AF$9,0) -> 0 | AG109: =VLOOKUP($E109,[1]Sheet1!$E$10:$X$629,AG$9,0) -> 0 | AH109: =VLOOKUP($E109,[1]Sheet1!$E$10:$X$629,AH$9,0) -> 0 | AJ109: =SUM(M109:T109) -> 0 | AK109: =SUM(AA109:AH109) -> 0 | AL109: =IFERROR(AJ109-AK109,0) -> 0
A110: 810018879617 | B110: 2556435 | C110: SHADE STICK FOUNDATION | E110: 1000161 | F110: 021 | G110: 3453 - JUVIA'S PLACE | I110: X | J110: BASC | K110: 8 | L110: 3.99 | M110: 0 | N110: 0 | O110: 0 | P110: 0 | Q110: 0 | R110: 0 | S110: 0 | T110: 0 | U110: 0 | V110: 0 | W110: 0 | X110: 0 | Z110: =VLOOKUP(E110,Sheet2!$A$1:$A$39,1,0) -> #N/A | AA110: =VLOOKUP($E110,[1]Sheet1!$E$10:$X$629,AA$9,0) -> 0 | AB110: =VLOOKUP($E110,[1]Sheet1!$E$10:$X$629,AB$9,0) -> 0 | AC110: =VLOOKUP($E110,[1]Sheet1!$E$10:$X$629,AC$9,0) -> 0 | AD110: =VLOOKUP($E110,[1]Sheet1!$E$10:$X$629,AD$9,0) -> 0 | AE110: =VLOOKUP($E110,[1]Sheet1!$E$10:$X$629,AE$9,0) -> 0 | AF110: =VLOOKUP($E110,[1]Sheet1!$E$10:$X$629,AF$9,0) -> 0 | AG110: =VLOOKUP($E110,[1]Sheet1!$E$10:$X$629,AG$9,0) -> 0 | AH110: =VLOOKUP($E110,[1]Sheet1!$E$10:$X$629,AH$9,0) -> 0 | AJ110: =SUM(M110:T110) -> 0 | AK110: =SUM(AA110:AH110) -> 0 | AL110: =IFERROR(AJ110-AK110,0) -> 0
A111: 810018879624 | B111: 2556436 | C111: SHADE STICK FOUNDATION | E111: 1000176 | F111: 021 | G111: 3453 - JUVIA'S PLACE | I111: X | J111: BASC | K111: 8 | L111: 3.99 | M111: 0 | N111: 0 | O111: 0 | P111: 0 | Q111: 0 | R111: 0 | S111: 0 | T111: 0 | U111: 0 | V111: 0 | W111: 0 | X111: 0 | Z111: =VLOOKUP(E111,Sheet2!$A$1:$A$39,1,0) -> #N/A | AA111: =VLOOKUP($E111,[1]Sheet1!$E$10:$X$629,AA$9,0) -> 0 | AB111: =VLOOKUP($E111,[1]Sheet1!$E$10:$X$629,AB$9,0) -> 0 | AC111: =VLOOKUP($E111,[1]Sheet1!$E$10:$X$629,AC$9,0) -> 0 | AD111: =VLOOKUP($E111,[1]Sheet1!$E$10:$X$629,AD$9,0) -> 0 | AE111: =VLOOKUP($E111,[1]Sheet1!$E$10:$X$629,AE$9,0) -> 0 | AF111: =VLOOKUP($E111,[1]Sheet1!$E$10:$X$629,AF$9,0) -> 0 | AG111: =VLOOKUP($E111,[1]Sheet1!$E$10:$X$629,AG$9,0) -> 0 | AH111: =VLOOKUP($E111,[1]Sheet1!$E$10:$X$629,AH$9,0) -> 0 | AJ111: =SUM(M111:T111) -> 0 | AK111: =SUM(AA111:AH111) -> 0 | AL111: =IFERROR(AJ111-AK111,0) -> 0
A112: 810018879679 | B112: 2556437 | C112: SHADE STICK FOUNDATION | E112: 1000167 | F112: 021 | G112: 3453 - JUVIA'S PLACE | I112: X | J112: BASC | K112: 8 | L112: 3.99 | M112: 0 | N112: 0 | O112: 0 | P112: 0 | Q112: 0 | R112: 0 | S112: 0 | T112: 0 | U112: 0 | V112: 0 | W112: 0 | X112: 0 | Z112: =VLOOKUP(E112,Sheet2!$A$1:$A$39,1,0) -> #N/A | AA112: =VLOOKUP($E112,[1]Sheet1!$E$10:$X$629,AA$9,0) -> 0 | AB112: =VLOOKUP($E112,[1]Sheet1!$E$10:$X$629,AB$9,0) -> 0 | AC112: =VLOOKUP($E112,[1]Sheet1!$E$10:$X$629,AC$9,0) -> 0 | AD112: =VLOOKUP($E112,[1]Sheet1!$E$10:$X$629,AD$9,0) -> 0 | AE112: =VLOOKUP($E112,[1]Sheet1!$E$10:$X$629,AE$9,0) -> 0 | AF112: =VLOOKUP($E112,[1]Sheet1!$E$10:$X$629,AF$9,0) -> 0 | AG112: =VLOOKUP($E112,[1]Sheet1!$E$10:$X$629,AG$9,0) -> 0 | AH112: =VLOOKUP($E112,[1]Sheet1!$E$10:$X$629,AH$9,0) -> 0 | AJ112: =SUM(M112:T112) -> 0 | AK112: =SUM(AA112:AH112) -> 0 | AL112: =IFERROR(AJ112-AK112,0) -> 0
A113: 810018879570 | B113: 2556438 | C113: SHADE STICK FOUNDATION | E113: 1000166 | F113: 021 | G113: 3453 - JUVIA'S PLACE | I113: X | J113: BASC | K113: 8 | L113: 3.99 | M113: 0 | N113: 0 | O113: 0 | P113: 0 | Q113: 0 | R113: 0 | S113: 0 | T113: 0 | U113: 0 | V113: 0 | W113: 0 | X113: 0 | Z113: =VLOOKUP(E113,Sheet2!$A$1:$A$39,1,0) -> #N/A | AA113: =VLOOKUP($E113,[1]Sheet1!$E$10:$X$629,AA$9,0) -> 0 | AB113: =VLOOKUP($E113,[1]Sheet1!$E$10:$X$629,AB$9,0) -> 0 | AC113: =VLOOKUP($E113,[1]Sheet1!$E$10:$X$629,AC$9,0) -> 0 | AD113: =VLOOKUP($E113,[1]Sheet1!$E$10:$X$629,AD$9,0) -> 0 | AE113: =VLOOKUP($E113,[1]Sheet1!$E$10:$X$629,AE$9,0) -> 0 | AF113: =VLOOKUP($E113,[1]Sheet1!$E$10:$X$629,AF$9,0) -> 0 | AG113: =VLOOKUP($E113,[1]Sheet1!$E$10:$X$629,AG$9,0) -> 0 | AH113: =VLOOKUP($E113,[1]Sheet1!$E$10:$X$629,AH$9,0) -> 0 | AJ113: =SUM(M113:T113) -> 0 | AK113: =SUM(AA113:AH113) -> 0 | AL113: =IFERROR(AJ113-AK113,0) -> 0
A114: 810018879587 | B114: 2556439 | C114: SHADE STICK FOUNDATION | E114: 1000175 | F114: 021 | G114: 3453 - JUVIA'S PLACE | I114: X | J114: BASC | K114: 8 | L114: 3.99 | M114: 0 | N114: 0 | O114: 0 | P114: 0 | Q114: 0 | R114: 0 | S114: 0 | T114: 0 | U114: 0 | V114: 0 | W114: 0 | X114: 0 | Z114: =VLOOKUP(E114,Sheet2!$A$1:$A$39,1,0) -> #N/A | AA114: =VLOOKUP($E114,[1]Sheet1!$E$10:$X$629,AA$9,0) -> 0 | AB114: =VLOOKUP($E114,[1]Sheet1!$E$10:$X$629,AB$9,0) -> 0 | AC114: =VLOOKUP($E114,[1]Sheet1!$E$10:$X$629,AC$9,0) -> 0 | AD114: =VLOOKUP($E114,[1]Sheet1!$E$10:$X$629,AD$9,0) -> 0 | AE114: =VLOOKUP($E114,[1]Sheet1!$E$10:$X$629,AE$9,0) -> 0 | AF114: =VLOOKUP($E114,[1]Sheet1!$E$10:$X$629,AF$9,0) -> 0 | AG114: =VLOOKUP($E114,[1]Sheet1!$E$10:$X$629,AG$9,0) -> 0 | AH114: =VLOOKUP($E114,[1]Sheet1!$E$10:$X$629,AH$9,0) -> 0 | AJ114: =SUM(M114:T114) -> 0 | AK114: =SUM(AA114:AH114) -> 0 | AL114: =IFERROR(AJ114-AK114,0) -> 0
A115: 810018879457 | B115: 2556440 | C115: SHADE STICK FOUNDATION | E115: 1000159 | F115: 021 | G115: 3453 - JUVIA'S PLACE | I115: X | J115: BASC | K115: 8 | L115: 3.99 | M115: 0 | N115: 0 | O115: 0 | P115: 0 | Q115: 0 | R115: 0 | S115: 0 | T115: 0 | U115: 0 | V115: 0 | W115: 0 | X115: 0 | Z115: =VLOOKUP(E115,Sheet2!$A$1:$A$39,1,0) -> #N/A | AA115: =VLOOKUP($E115,[1]Sheet1!$E$10:$X$629,AA$9,0) -> 0 | AB115: =VLOOKUP($E115,[1]Sheet1!$E$10:$X$629,AB$9,0) -> 0 | AC115: =VLOOKUP($E115,[1]Sheet1!$E$10:$X$629,AC$9,0) -> 0 | AD115: =VLOOKUP($E115,[1]Sheet1!$E$10:$X$629,AD$9,0) -> 0 | AE115: =VLOOKUP($E115,[1]Sheet1!$E$10:$X$629,AE$9,0) -> 0 | AF115: =VLOOKUP($E115,[1]Sheet1!$E$10:$X$629,AF$9,0) -> 0 | AG115: =VLOOKUP($E115,[1]Sheet1!$E$10:$X$629,AG$9,0) -> 0 | AH115: =VLOOKUP($E115,[1]Sheet1!$E$10:$X$629,AH$9,0) -> 0 | AJ115: =SUM(M115:T115) -> 0 | AK115: =SUM(AA115:AH115) -> 0 | AL115: =IFERROR(AJ115-AK115,0) -> 0
A116: 810018879655 | B116: 2556441 | C116: SHADE STICK FOUNDATION | E116: 1000182 | F116: 021 | G116: 3453 - JUVIA'S PLACE | I116: X | J116: BASC | K116: 8 | L116: 3.99 | M116: 0 | N116: 0 | O116: 0 | P116: 0 | Q116: 0 | R116: 0 | S116: 0 | T116: 0 | U116: 0 | V116: 0 | W116: 0 | X116: 0 | Z116: =VLOOKUP(E116,Sheet2!$A$1:$A$39,1,0) -> #N/A | AA116: =VLOOKUP($E116,[1]Sheet1!$E$10:$X$629,AA$9,0) -> 0 | AB116: =VLOOKUP($E116,[1]Sheet1!$E$10:$X$629,AB$9,0) -> 0 | AC116: =VLOOKUP($E116,[1]Sheet1!$E$10:$X$629,AC$9,0) -> 0 | AD116: =VLOOKUP($E116,[1]Sheet1!$E$10:$X$629,AD$9,0) -> 0 | AE116: =VLOOKUP($E116,[1]Sheet1!$E$10:$X$629,AE$9,0) -> 0 | AF116: =VLOOKUP($E116,[1]Sheet1!$E$10:$X$629,AF$9,0) -> 0 | AG116: =VLOOKUP($E116,[1]Sheet1!$E$10:$X$629,AG$9,0) -> 0 | AH116: =VLOOKUP($E116,[1]Sheet1!$E$10:$X$629,AH$9,0) -> 0 | AJ116: =SUM(M116:T116) -> 0 | AK116: =SUM(AA116:AH116) -> 0 | AL116: =IFERROR(AJ116-AK116,0) -> 0
A117: 810018879358 | B117: 2556442 | C117: SHADE STICK FOUNDATION | E117: 1000168 | F117: 021 | G117: 3453 - JUVIA'S PLACE | I117: X | J117: BASC | K117: 8 | L117: 3.99 | M117: 0 | N117: 0 | O117: 0 | P117: 0 | Q117: 0 | R117: 0 | S117: 0 | T117: 0 | U117: 0 | V117: 0 | W117: 0 | X117: 0 | Z117: =VLOOKUP(E117,Sheet2!$A$1:$A$39,1,0) -> #N/A | AA117: =VLOOKUP($E117,[1]Sheet1!$E$10:$X$629,AA$9,0) -> 0 | AB117: =VLOOKUP($E117,[1]Sheet1!$E$10:$X$629,AB$9,0) -> 0 | AC117: =VLOOKUP($E117,[1]Sheet1!$E$10:$X$629,AC$9,0) -> 0 | AD117: =VLOOKUP($E117,[1]Sheet1!$E$10:$X$629,AD$9,0) -> 0 | AE117: =VLOOKUP($E117,[1]Sheet1!$E$10:$X$629,AE$9,0) -> 0 | AF117: =VLOOKUP($E117,[1]Sheet1!$E$10:$X$629,AF$9,0) -> 0 | AG117: =VLOOKUP($E117,[1]Sheet1!$E$10:$X$629,AG$9,0) -> 0 | AH117: =VLOOKUP($E117,[1]Sheet1!$E$10:$X$629,AH$9,0) -> 0 | AJ117: =SUM(M117:T117) -> 0 | AK117: =SUM(AA117:AH117) -> 0 | AL117: =IFERROR(AJ117-AK117,0) -> 0
A118: 810018879648 | B118: 2556443 | C118: SHADE STICK FOUNDATION | E118: 1000183 | F118: 021 | G118: 3453 - JUVIA'S PLACE | I118: X | J118: BASC | K118: 8 | L118: 3.99 | M118: 0 | N118: 0 | O118: 0 | P118: 0 | Q118: 0 | R118: 0 | S118: 0 | T118: 0 | U118: 0 | V118: 0 | W118: 0 | X118: 0 | Z118: =VLOOKUP(E118,Sheet2!$A$1:$A$39,1,0) -> #N/A | AA118: =VLOOKUP($E118,[1]Sheet1!$E$10:$X$629,AA$9,0) -> 0 | AB118: =VLOOKUP($E118,[1]Sheet1!$E$10:$X$629,AB$9,0) -> 0 | AC118: =VLOOKUP($E118,[1]Sheet1!$E$10:$X$629,AC$9,0) -> 0 | AD118: =VLOOKUP($E118,[1]Sheet1!$E$10:$X$629,AD$9,0) -> 0 | AE118: =VLOOKUP($E118,[1]Sheet1!$E$10:$X$629,AE$9,0) -> 0 | AF118: =VLOOKUP($E118,[1]Sheet1!$E$10:$X$629,AF$9,0) -> 0 | AG118: =VLOOKUP($E118,[1]Sheet1!$E$10:$X$629,AG$9,0) -> 0 | AH118: =VLOOKUP($E118,[1]Sheet1!$E$10:$X$629,AH$9,0) -> 0 | AJ118: =SUM(M118:T118) -> 0 | AK118: =SUM(AA118:AH118) -> 0 | AL118: =IFERROR(AJ118-AK118,0) -> 0
... A136: 810018879365 | B136: 2556461 | C136: SHADE STICK FOUNDATION | E136: 1000153 | F136: 021 | G136: 3453 - JUVIA'S PLACE | I136: X | J136: BASC | K136: 8 | L136: 3.99 | M136: 0 | N136: 0 | O136: 0 | P136: 0 | Q136: 0 | R136: 0 | S136: 0 | T136: 0 | U136: 0 | V136: 0 | W136: 0 | X136: 0 | Z136: =VLOOKUP(E136,Sheet2!$A$1:$A$39,1,0) -> #N/A | AA136: =VLOOKUP($E136,[1]Sheet1!$E$10:$X$629,AA$9,0) -> 0 | AB136: =VLOOKUP($E136,[1]Sheet1!$E$10:$X$629,AB$9,0) -> 0 | AC136: =VLOOKUP($E136,[1]Sheet1!$E$10:$X$629,AC$9,0) -> 0 | AD136: =VLOOKUP($E136,[1]Sheet1!$E$10:$X$629,AD$9,0) -> 0 | AE136: =VLOOKUP($E136,[1]Sheet1!$E$10:$X$629,AE$9,0) -> 0 | AF136: =VLOOKUP($E136,[1]Sheet1!$E$10:$X$629,AF$9,0) -> 0 | AG136: =VLOOKUP($E136,[1]Sheet1!$E$10:$X$629,AG$9,0) -> 0 | AH136: =VLOOKUP($E136,[1]Sheet1!$E$10:$X$629,AH$9,0) -> 0 | AJ136: =SUM(M136:T136) -> 0 | AK136: =SUM(AA136:AH136) -> 0 | AL136: =IFERROR(AJ136-AK136,0) -> 0
A137: 810018879983 | B137: 2557327 | C137: THE EYESHADOW PALETTE NOMAD | E137: 1000087 | F137: 021 | G137: 3453 - JUVIA'S PLACE | H137: E | I137: DI | J137: BASC | K137: 8.5 | L137: 17 | M137: 0 | N137: 0 | O137: 0 | P137: 0 | Q137: 0 | R137: 0 | S137: 0 | T137: 0 | U137: 0 | V137: 0 | W137: 0 | X137: 0 | Z137: =VLOOKUP(E137,Sheet2!$A$1:$A$39,1,0) -> #N/A | AA137: =VLOOKUP($E137,[1]Sheet1!$E$10:$X$629,AA$9,0) -> 0 | AB137: =VLOOKUP($E137,[1]Sheet1!$E$10:$X$629,AB$9,0) -> 0 | AC137: =VLOOKUP($E137,[1]Sheet1!$E$10:$X$629,AC$9,0) -> 0 | AD137: =VLOOKUP($E137,[1]Sheet1!$E$10:$X$629,AD$9,0) -> 0 | AE137: =VLOOKUP($E137,[1]Sheet1!$E$10:$X$629,AE$9,0) -> 0 | AF137: =VLOOKUP($E137,[1]Sheet1!$E$10:$X$629,AF$9,0) -> 0 | AG137: =VLOOKUP($E137,[1]Sheet1!$E$10:$X$629,AG$9,0) -> 0 | AH137: =VLOOKUP($E137,[1]Sheet1!$E$10:$X$629,AH$9,0) -> 0 | AJ137: =SUM(M137:T137) -> 0 | AK137: =SUM(AA137:AH137) -> 0 | AL137: =IFERROR(AJ137-AK137,0) -> 0
A138: 810018879327 | B138: 2564699 | C138: EYESHADOW PALETTE NUDES | E138: 1000094 | F138: 021 | G138: 3453 - JUVIA'S PLACE | H138: F | I138: A | J138: BASC | K138: 10 | L138: 20 | M138: 324 | N138: 108 | O138: 540 | P138: 432 | Q138: 216 | R138: 432 | S138: 432 | T138: 540 | U138: 648 | V138: 1620 | W138: 540 | X138: 1512 | Z138: =VLOOKUP(E138,Sheet2!$A$1:$A$39,1,0) -> #N/A | AA138: =VLOOKUP($E138,[1]Sheet1!$E$10:$X$629,AA$9,0) -> 432 | AB138: =VLOOKUP($E138,[1]Sheet1!$E$10:$X$629,AB$9,0) -> 864 | AC138: =VLOOKUP($E138,[1]Sheet1!$E$10:$X$629,AC$9,0) -> 756 | AD138: =VLOOKUP($E138,[1]Sheet1!$E$10:$X$629,AD$9,0) -> 648 | AE138: =VLOOKUP($E138,[1]Sheet1!$E$10:$X$629,AE$9,0) -> 864 | AF138: =VLOOKUP($E138,[1]Sheet1!$E$10:$X$629,AF$9,0) -> 540 | AG138: =VLOOKUP($E138,[1]Sheet1!$E$10:$X$629,AG$9,0) -> 756 | AH138: =VLOOKUP($E138,[1]Sheet1!$E$10:$X$629,AH$9,0) -> 216 | AJ138: =SUM(M138:T138) -> 3024 | AK138: =SUM(AA138:AH138) -> 5076 | AL138: =IFERROR(AJ138-AK138,0) -> -2052
A139: 810018879310 | B139: 2564700 | C139: EYESHADOW PALETTE VIOLETS | E139: 1000095 | F139: 021 | G139: 3453 - JUVIA'S PLACE | H139: E | I139: A | J139: BASC | K139: 10 | L139: 20 | M139: 432 | N139: 972 | O139: 756 | P139: 864 | Q139: 756 | R139: 864 | S139: 864 | T139: 1728 | U139: 1404 | V139: 1944 | W139: 540 | X139: 1944 | Z139: =VLOOKUP(E139,Sheet2!$A$1:$A$39,1,0) -> #N/A | AA139: =VLOOKUP($E139,[1]Sheet1!$E$10:$X$629,AA$9,0) -> 648 | AB139: =VLOOKUP($E139,[1]Sheet1!$E$10:$X$629,AB$9,0) -> 1188 | AC139: =VLOOKUP($E139,[1]Sheet1!$E$10:$X$629,AC$9,0) -> 972 | AD139: =VLOOKUP($E139,[1]Sheet1!$E$10:$X$629,AD$9,0) -> 756 | AE139: =VLOOKUP($E139,[1]Sheet1!$E$10:$X$629,AE$9,0) -> 756 | AF139: =VLOOKUP($E139,[1]Sheet1!$E$10:$X$629,AF$9,0) -> 1080 | AG139: =VLOOKUP($E139,[1]Sheet1!$E$10:$X$629,AG$9,0) -> 864 | AH139: =VLOOKUP($E139,[1]Sheet1!$E$10:$X$629,AH$9,0) -> 432 | AJ139: =SUM(M139:T139) -> 7236 | AK139: =SUM(AA139:AH139) -> 6696 | AL139: =IFERROR(AJ139-AK139,0) -> 540
A140: 810018879334 | B140: 2564701 | C140: EYESHADOW PALETTE BERRIES | E140: 1000092 | F140: 021 | G140: 3453 - JUVIA'S PLACE | H140: D | I140: X | J140: BASC | K140: 7.5 | L140: 3.75 | M140: 0 | N140: 0 | O140: 0 | P140: 0 | Q140: 0 | R140: 0 | S140: 0 | T140: 0 | U140: 0 | V140: 0 | W140: 0 | X140: 0 | Z140: =VLOOKUP(E140,Sheet2!$A$1:$A$39,1,0) -> #N/A | AA140: =VLOOKUP($E140,[1]Sheet1!$E$10:$X$629,AA$9,0) -> 0 | AB140: =VLOOKUP($E140,[1]Sheet1!$E$10:$X$629,AB$9,0) -> 0 | AC140: =VLOOKUP($E140,[1]Sheet1!$E$10:$X$629,AC$9,0) -> 0 | AD140: =VLOOKUP($E140,[1]Sheet1!$E$10:$X$629,AD$9,0) -> 0 | AE140: =VLOOKUP($E140,[1]Sheet1!$E$10:$X$629,AE$9,0) -> 0 | AF140: =VLOOKUP($E140,[1]Sheet1!$E$10:$X$629,AF$9,0) -> 0 | AG140: =VLOOKUP($E140,[1]Sheet1!$E$10:$X$629,AG$9,0) -> 0 | AH140: =VLOOKUP($E140,[1]Sheet1!$E$10:$X$629,AH$9,0) -> 0 | AJ140: =SUM(M140:T140) -> 0 | AK140: =SUM(AA140:AH140) -> 0 | AL140: =IFERROR(AJ140-AK140,0) -> 0
...

Sheet Sheet2
A1: 1200777
A2: 1200785
A3: 1200786
A4: 1200742
A5: 1200743
A6: 1200744
A7: 1200745
A8: 1200746
A9: 1200768
A10: 1200769
A11: 1200770
A12: 1200771
... A39: 1200898

Sheet Definitions_and_Disclaimer
A2: Brand Partner Order Projections
A3: Definitions and Disclaimer
A4: JUVIA'S PLACE (52853)
A5: Report Generated: 1/28/2026 8:15:30 PM
A7: Order Projections Disclaimer The projections contained in this report reflect a systematic output generated at a point of time and are subject to change based on selling patterns, changes to assortment, promotions, or ability to fulfill orders. These projected order quantities are not a guarantee of purchase and should be used as a directional estimate for planning purposes. Please reach out to your Ulta Beauty team for further assistance.
C9: Definitions
B10: Column Title | C10: UPC | D10: ULTA Item# | E10: ULTA Item Description | G10: Brand Partner SKU# | I10: Brand # | J10: Retail Item Rank | K10: Feature Code | L10: Season Code | N10: Purch Cost (Average) | O10: Retail Price (Current)
B11: Definition | C11: "Universal Product Code" is a unique identifier which may be used as an alternate to ULTA's Item number | D11: ULTA's internal identifier for a specific product | E11: ULTA's internal plain text description for a specific product | G11: A Brand Partner's internal identifier for a specific product | I11: ULTA's internal classification for like Items belonging to the same brand | J11: Enterprise performance rank given to Items based on their sales velocity in relation to other Items in retail locations | K11: Identifier given to an Item which aids in determining where an Item is sold | L11: Identifier given to an Item which determines if it is part of ULTA's base assortment, promotional, or seasonal. | N11: The average price ULTA has been charged to acquire an Item | O11: The cost that ULTA is currently charging customers for an Item
B12: Possible Values | C12: N/A | D12: N/A | E12: N/A | G12: N/A | I12: N/A | J12: A - Top 25% B - Next 25% C - Next 20% D - Next 15% E - Next 10% F - Next 5% N/A - Not assigned | K12: AA - All Stores H* - High Volatile L* - Low Volatile U* - Unique TT - Testers Z* - Discontinued | L12: BASC - Basic PROM - Promotional IO* - In and Out SE* - Seasonal | N12: N/A | O12: N/A
